Workbook

Sheet Cover
A1: LIIBAN SMART MALL — Integrated Financial Model
A2: TDOMA S.C. · G+15 mixed-use trade complex · Merkato, Addis Ababa
A4: Version | B4: 2.0
A5: Date | B5: 20 July 2026 (audited/edited)
A6: Author | B6: Prepared for TDOMA S.C.
A7: Reporting currency | B7: ETB (Ethiopian Birr); USD memo @ 160
A8: Framework | B8: Full IFRS (Financial Reporting Proclamation No. 847/2014, AABE)
A9: Structure | B9: 70/30 PPP with City Government of Addis Ababa
A10: Presentation | B10: Consolidated 100%; City's 30% as non-controlling interest
A11: Horizon | B11: 3 construction years + 12 operating years; statements shown for 10
A13: CONVENTIONS
A14: BLUE | B14: Input — change these
A15: BLACK | B15: Formula within the sheet
A16: GREEN | B16: Cross-sheet link
A17: YELLOW fill | B17: Key output or check
A19: CIRCULARITY
A20: None | B20: The model is fully ACYCLIC. No iterative calculation is required or enabled.
B21: The monthly IDC schedule is RECURSIVE (month m depends on month m-1), which
B22: Excel handles natively. The one true cycle (arrangement fee <-> IDC) was removed
B23: by excluding IDC from the fee base: a 0.047% effect on capex, in exchange for a
B24: workbook that cannot break on a settings change and is independently verifiable.
A26: HOW TO CHANGE AN INPUT
A27: 1 | B27: Go to the Assumptions sheet. Change any BLUE cell.
A28: 2 | B28: Everything downstream re-calculates — no hard-coded outputs anywhere.
A29: 3 | B29: Check the Checks sheet. Do not rely on the model if anything reads FAIL
B30: (except the DSCR check — see below).
A32: VALUE-ENGINEERING APPLIED
A33: Facade | B33: Kinetic bronze shading -> standard curtain walling (BOQ D.2)
A34: Data centre | B34: On-site data centre -> cloud infrastructure (BOQ I.2 dropped; opex added)
A35: ASRS | B35: Automated logistics dropped; B2+B3 (6,000 m2) let as warehouse instead of service area
A36: Office | B36: Community/civic, museum/craft, enterprise/digital, business centre CONSOLIDATED
B37: into commercial office: 2,592 -> 5,264 m2
A38: Key money | B38: Set to ZERO — TDOMA cannot charge it (one-time payment between an incoming
B39: tenant and an OUTGOING tenant/broker on a vacant lease; not applicable to a first landlord)
A41: KNOWN FINDINGS
A42: DSCR | B42: ="Minimum DSCR is "&TEXT(Returns!$B$19,"0.00")&"x — "&IF(Returns!$B$19>=DSCR_COV,"clears","BREACHES")&" the "&TEXT(DSCR_COV,"0.00")&"x covenant." -> Minimum DSCR is 1.42x — clears the 1.30x covenant.
B43: See Dashboard.
A44: Viability | B44: ="Project IRR "&TEXT(Returns!$B$12,"0.0%")&", equity IRR "&TEXT(Returns!$B$14,"0.0%")&" — "&IF(Returns!$B$12>=DISC,"clears","MISSES")&" the "&TEXT(DISC,"0%")&" project hurdle; "&IF(Returns!$B$14>=EQ_HURDLE,"clears","MISSES")&" the "&TEXT(EQ_HURDLE,"0%")&" equity hurdle." -> Project IRR 28.3%, equity IRR 24.2% — clears the 20% project hurdle; clears the 24% equity hurdle.
B45: See Dashboard.
A46: Floor, not estimate | B46: Specialist consultancy is priced from industry norms; warehouse rent has no
B47: sourced comparable yet.
A48: Impairment (IAS 36) | B48: Test IS performed (see Returns). Value in use exceeds carrying value every year; no
B49: charge is booked in the P&L/BS -- would need separate modelling if a scenario ever breaches it.
A50: Related-party sale — LEGAL ACTION REQUIRED | B50: The 1,684,800,000 ETB retail sale to shareholder-
B51: merchants has NO recorded Art. 395 board/shareholder approval, auditor's report, or MoTI filing
B52: on file. It remains legally VOIDABLE until obtained -- see TaxLaw. This is a governance/legal
B53: action a model cannot resolve; flagged here so it is not lost.
A55: SHEETS
A56: Assumptions | B56: Every input, with source, date and confidence flag
A57: TaxLaw | B57: Tax & Law Register + IFRS treatments applied
A58: Capex / IDC | B58: Development cost; IDC solved monthly
A59: AssetSplit | B59: IAS 2 / IAS 40 / IAS 16 allocation + depreciation basis
A60: Revenue / Opex | B60: Rent roll, sales, turnover rent, key money; operating costs
A61: Financing | B61: Loan amortisation + DSCR covenant
A62: Tax | B62: Current + deferred (IAS 12)
A63: VAT | B63: Output/input VAT and net position — live formulas
A64: PL / BS / CashFlow | B64: The three statements, integrated
A65: Returns | B65: DCF, IRRs, GDV vs cost
A66: Checks | B66: Integrity checks — all live formulas
A67: Sensitivity | B67: Delay, cost overrun, FX, revenue, financing — COMPUTED VALUES,
B68: not live formulas (see the sheet's own header). Detail: docs/05.
A69: Breakeven | B69: Occupancy / rent / sale-price / sale-% / exit-cap break-evens
B70: against margin, DSCR and IRR targets. Computed. Detail: docs/06.
A72: AUDIT LOG (this version)
B73: 1. Cover/Dashboard headline IRR/DSCR sentences were stale hard-typed text, contradicting the live model and the Sensitivity sheet's own commentary — converted to live formulas (B42, B44 here; Dashboard!A35:A36).
B74: 2. FF&E (7-yr life) was being depreciated for the full 12-yr horizon instead of stopping at year 7 — fixed via new AssetSplit!rows45-52; flows through to PL, Balancesheet, Tax.
B75: 3. Project/Equity IRR cash flows omitted the O1 input-VAT capex refund that Cash Flow and the DSCR test both included — fixed in Returns!row4.
B76: 4. VAT sheet row 10 summed the capex refund despite its own note saying not to — fixed; memo row 14 added.
B77: 5. Returns!A5 label said "75% share out"; formula used 70% — label corrected.
B78: 6. AssetSplit!B10 had two unlabeled hard-coded rate/area pairs — linked to new Assumptions!B94:B97.
B79: 7. Sensitivity sheet "Base" cells in every table re-linked to the live model (were a stale snapshot); non-base scenario rows still need re-simulation (see note in sheet).
B80: 8. Added Assumptions!B98 (Equity IRR hurdle, 24%) since no source cell previously existed for a figure quoted repeatedly elsewhere.
B81: Net effect: corrected Project IRR 29.7%, Equity IRR 25.3% (now genuinely clears the 24% hurdle), Min DSCR 1.42x. All 13 integrity checks still PASS; balance sheet still balances exactly.
B82: 9. Sensitivity and Breakeven sheets FULLY RECOMPUTED against the corrected model (previously stale externally-computed snapshots). Method: a Python replica of the workbook, validated to 1.6e-14 at base case, then spot-verified by re-running 7 scenarios and 8 break-even points through LibreOffice on the actual workbook (worst deviation 8.9e-14).
B83: 10. NEW FINDINGS from the recomputation: (a) the DSCR covenant, not the IRR hurdle, is the binding constraint - it breaches at ~7% cost overrun, 0.85x occupancy, or a 25.3% debt rate, while project IRR still looks healthy; (b) OCC_MULT and a uniform rent multiplier are the SAME lever mathematically, so Breakeven tables A and B must agree - the original showed different numbers; (c) EXIT_CAP does double duty as terminal cap rate AND property-tax valuation yield, contaminating the exit-cap sensitivity.

Sheet Assumptions
A1: Assumptions Register
A3: Item | B3: Value
A4: AREAS — Programme (Area Allocation Matrix)
A5: Plot area | B5: 5000
A6: Above-grade gross (INCL 600 m2 roof) | B6: 28800
A7: Basement gross (3 levels) | B7: 9000
A8: Total net GLA | B8: 21004
A9: Retail — total net GLA | B9: 4160
A10: Retail — % sold after construction | B10: 0.75
A11: TDOMA HQ (owner-occupied) | B11: 864
A12: Government one-stop (rent-free) | B12: 320
A13: Basement warehouse area (B2+B3) | B13: 6000
A14: Arrival & circulation (no rent) | B14: 500
A15: Hotel net GLA | B15: 1728
A16: Events & MICE net GLA | B16: 3084
A17: Occupancy level multiplier (sensitivity) | B17: 1
A18: CONSTRUCTION — BOQ elemental
A19: BOQ A Preliminaries & General | B19: 424000000
A20: BOQ B Substructure | B20: 692800000
A21: BOQ C Superstructure | B21: 716900000
A22: BOQ D External Envelope | B22: 428000000
A23: BOQ E Internal Divisions | B23: 164900000
A24: BOQ F Finishes | B24: 381870000
A25: BOQ G Fittings & Sanitary | B25: 106000000
A26: BOQ H Services / MEP | B26: 899280000
A27: BOQ I Specialist Systems | B27: 158250000
A28: BOQ J External Works | B28: 92100000
A29: In-house design fee % | B29: 0.02
A30: Contingency % | B30: 0.12
... A33: Pre-opening & marketing | B33: 120000000
A34: LAND — City's in-kind contribution
A35: Land rate | B35: 330000
A36: FINANCING
A37: Loan interest rate | B37: 0.2
A38: Debt share of cash requirement | B38: 0.25
A39: Arrangement fee % | B39: 0.015
A40: Construction period | B40: 36
A41: Grace period | B41: 3
A42: Loan tenor | B42: 7
A43: DSCR covenant | B43: 1.3
A44: REVENUE RATES
A45: Retail contract rent | B45: 6250
A46: Key money (TDOMA cannot charge) | B46: 0
A47: Retail sale price | B47: 540000
A48: Office rent | B48: 4600
A49: Wholesale showrooms rent | B49: 4600
A50: Trade services rent | B50: 5625
A51: Basement warehouse rent | B51: 3500
A52: Hotel keys | B52: 38
A53: Hotel ADR | B53: 12800
A54: Hotel F&B uplift | B54: 0.5
A55: Hotel turnover rent | B55: 0.25
A56: Events / expo / AGM hire | B56: 96000000
... A59: Service charge, ads, fintech | B59: 48000000
A60: OPERATING
A61: Property opex (% of stabilised rent) | B61: 0.25
A62: Management fee (% of gross revenue) | B62: 0.04
A63: Property tax (% of assessed value) | B63: 0.01
A64: Bad debt (% of billed rent) | B64: 0.02
A65: Cloud infrastructure opex | B65: 12000000
A66: Rent escalation p.a. | B66: 0.25
A67: Opex escalation p.a. | B67: 0.05
A68: ADR growth p.a. | B68: 0.07
A69: Occupancy — Year 1 | B69: 0.75
A70: Occupancy — Year 2 | B70: 0.85
A71: Occupancy — stabilised | B71: 0.95
A72: Hotel occupancy — Year 1 | B72: 0.6
... A75: Dividend payout (% of PAT) | B75: 0.5
A76: TAX & MACRO
A77: Corporate income tax | B77: 0.3
A78: VAT | B78: 0.15
A79: Tax depreciation - building pool | B79: 0.05
A80: Tax depreciation - plant & machinery pool | B80: 0.2
A81: Dividend withholding | B81: 0.15
A82: Undistributed-profits tax | B82: 0
A83: Legal reserve (% of net profit) | B83: 0
A84: Loss carry-forward cap | B84: 0
A85: FX ETB/USD | B85: 160
A86: Discount rate (DCF hurdle) | B86: 0.2
A87: Cost of equity | B87: 0.2
A88: Terminal / exit cap rate | B88: 0.105
A89: ACCOUNTING LIVES
A90: Building useful life | B90: 50
A91: Specialist systems useful life | B91: 15
A92: FF&E useful life | B92: 7
A93: AUDIT-ADDED — previously hard-coded inline (see cell comments)
A94: HQ plant/roof area (m2) — was hard-coded in AssetSplit!B10 | B94: 600
A95: HQ plant/roof fit-out rate (ETB/m2) — was hard-coded in AssetSplit!B10 | B95: 25000
A96: HQ secondary fit-out area (m2) — was hard-coded in AssetSplit!B10 | B96: 264
A97: HQ secondary fit-out rate (ETB/m2) — was hard-coded in AssetSplit!B10 | B97: 35000
A98: Equity IRR hurdle — was hard-coded only in Breakeven!B65/Sensitivity notes as 24%; no other source cell existed. CONFIRM SOURCE. | B98: 0.24

Sheet IDC
A1: Interest During Construction
A2: Month | B2: S-curve draw | C2: Civils spend | D2: FF&E + pre-open | E2: Arr. fee | F2: Opening debt | G2: Interest | H2: Debt draw | I2: Closing debt
A3: 1 | B3: =(3*(A3/CONSTR_M)^2-2*(A3/CONSTR_M)^3)-(3*((A3-1)/CONSTR_M)^2-2*((A3-1)/CONSTR_M)^3) -> 0.0022719479 | C3: =B3*Capex!$B$9 -> 10591138 | D3: =IF(A3>CONSTR_M-6,(FFE+PREOPEN)/6,0) -> 0 | E3: =IF(A3=1,Capex!$B$15,0) -> 18542697 | F3: =0 -> 0 | G3: =F3*RATE/12 -> 0 | H3: =DEBT_SHARE*(C3+D3+E3+G3) -> 7283458.8 | I3: =F3+H3 -> 7283458.8
A4: 2 | B4: =(3*(A4/CONSTR_M)^2-2*(A4/CONSTR_M)^3)-(3*((A4-1)/CONSTR_M)^2-2*((A4-1)/CONSTR_M)^3) -> 0.0066443759 | C4: =B4*Capex!$B$9 -> 30974082 | D4: =IF(A4>CONSTR_M-6,(FFE+PREOPEN)/6,0) -> 0 | E4: =IF(A4=1,Capex!$B$15,0) -> 0 | F4: =I3 -> 7283458.8 | G4: =F4*RATE/12 -> 121390.98 | H4: =DEBT_SHARE*(C4+D4+E4+G4) -> 7773868.3 | I4: =F4+H4 -> 15057327
A5: 3 | B5: =(3*(A5/CONSTR_M)^2-2*(A5/CONSTR_M)^3)-(3*((A5-1)/CONSTR_M)^2-2*((A5-1)/CONSTR_M)^3) -> 0.010759602 | C5: =B5*Capex!$B$9 -> 50158030 | D5: =IF(A5>CONSTR_M-6,(FFE+PREOPEN)/6,0) -> 0 | E5: =IF(A5=1,Capex!$B$15,0) -> 0 | F5: =I4 -> 15057327 | G5: =F5*RATE/12 -> 250955.45 | H5: =DEBT_SHARE*(C5+D5+E5+G5) -> 12602246 | I5: =F5+H5 -> 27659573
A6: 4 | B6: =(3*(A6/CONSTR_M)^2-2*(A6/CONSTR_M)^3)-(3*((A6-1)/CONSTR_M)^2-2*((A6-1)/CONSTR_M)^3) -> 0.014617627 | C6: =B6*Capex!$B$9 -> 68142981 | D6: =IF(A6>CONSTR_M-6,(FFE+PREOPEN)/6,0) -> 0 | E6: =IF(A6=1,Capex!$B$15,0) -> 0 | F6: =I5 -> 27659573 | G6: =F6*RATE/12 -> 460992.89 | H6: =DEBT_SHARE*(C6+D6+E6+G6) -> 17150993 | I6: =F6+H6 -> 44810567
A7: 5 | B7: =(3*(A7/CONSTR_M)^2-2*(A7/CONSTR_M)^3)-(3*((A7-1)/CONSTR_M)^2-2*((A7-1)/CONSTR_M)^3) -> 0.01821845 | C7: =B7*Capex!$B$9 -> 84928935 | D7: =IF(A7>CONSTR_M-6,(FFE+PREOPEN)/6,0) -> 0 | E7: =IF(A7=1,Capex!$B$15,0) -> 0 | F7: =I6 -> 44810567 | G7: =F7*RATE/12 -> 746842.78 | H7: =DEBT_SHARE*(C7+D7+E7+G7) -> 21418944 | I7: =F7+H7 -> 66229511
A8: 6 | B8: =(3*(A8/CONSTR_M)^2-2*(A8/CONSTR_M)^3)-(3*((A8-1)/CONSTR_M)^2-2*((A8-1)/CONSTR_M)^3) -> 0.021562071 | C8: =B8*Capex!$B$9 -> 1.0051589e+08 | D8: =IF(A8>CONSTR_M-6,(FFE+PREOPEN)/6,0) -> 0 | E8: =IF(A8=1,Capex!$B$15,0) -> 0 | F8: =I7 -> 66229511 | G8: =F8*RATE/12 -> 1103825.2 | H8: =DEBT_SHARE*(C8+D8+E8+G8) -> 25404929 | I8: =F8+H8 -> 91634441
A9: 7 | B9: =(3*(A9/CONSTR_M)^2-2*(A9/CONSTR_M)^3)-(3*((A9-1)/CONSTR_M)^2-2*((A9-1)/CONSTR_M)^3) -> 0.024648491 | C9: =B9*Capex!$B$9 -> 1.1490385e+08 | D9: =IF(A9>CONSTR_M-6,(FFE+PREOPEN)/6,0) -> 0 | E9: =IF(A9=1,Capex!$B$15,0) -> 0 | F9: =I8 -> 91634441 | G9: =F9*RATE/12 -> 1527240.7 | H9: =DEBT_SHARE*(C9+D9+E9+G9) -> 29107773 | I9: =F9+H9 -> 1.2074221e+08
A10: 8 | B10: =(3*(A10/CONSTR_M)^2-2*(A10/CONSTR_M)^3)-(3*((A10-1)/CONSTR_M)^2-2*((A10-1)/CONSTR_M)^3) -> 0.027477709 | C10: =B10*Capex!$B$9 -> 1.2809282e+08 | D10: =IF(A10>CONSTR_M-6,(FFE+PREOPEN)/6,0) -> 0 | E10: =IF(A10=1,Capex!$B$15,0) -> 0 | F10: =I9 -> 1.2074221e+08 | G10: =F10*RATE/12 -> 2012370.2 | H10: =DEBT_SHARE*(C10+D10+E10+G10) -> 32526297 | I10: =F10+H10 -> 1.5326851e+08
A11: 9 | B11: =(3*(A11/CONSTR_M)^2-2*(A11/CONSTR_M)^3)-(3*((A11-1)/CONSTR_M)^2-2*((A11-1)/CONSTR_M)^3) -> 0.030049726 | C11: =B11*Capex!$B$9 -> 1.4008278e+08 | D11: =IF(A11>CONSTR_M-6,(FFE+PREOPEN)/6,0) -> 0 | E11: =IF(A11=1,Capex!$B$15,0) -> 0 | F11: =I10 -> 1.5326851e+08 | G11: =F11*RATE/12 -> 2554475.2 | H11: =DEBT_SHARE*(C11+D11+E11+G11) -> 35659315 | I11: =F11+H11 -> 1.8892783e+08
A12: 10 | B12: =(3*(A12/CONSTR_M)^2-2*(A12/CONSTR_M)^3)-(3*((A12-1)/CONSTR_M)^2-2*((A12-1)/CONSTR_M)^3) -> 0.03236454 | C12: =B12*Capex!$B$9 -> 1.5087375e+08 | D12: =IF(A12>CONSTR_M-6,(FFE+PREOPEN)/6,0) -> 0 | E12: =IF(A12=1,Capex!$B$15,0) -> 0 | F12: =I11 -> 1.8892783e+08 | G12: =F12*RATE/12 -> 3148797.1 | H12: =DEBT_SHARE*(C12+D12+E12+G12) -> 38505638 | I12: =F12+H12 -> 2.2743346e+08
A13: 11 | B13: =(3*(A13/CONSTR_M)^2-2*(A13/CONSTR_M)^3)-(3*((A13-1)/CONSTR_M)^2-2*((A13-1)/CONSTR_M)^3) -> 0.034422154 | C13: =B13*Capex!$B$9 -> 1.6046573e+08 | D13: =IF(A13>CONSTR_M-6,(FFE+PREOPEN)/6,0) -> 0 | E13: =IF(A13=1,Capex!$B$15,0) -> 0 | F13: =I12 -> 2.2743346e+08 | G13: =F13*RATE/12 -> 3790557.7 | H13: =DEBT_SHARE*(C13+D13+E13+G13) -> 41064072 | I13: =F13+H13 -> 2.6849754e+08
A14: 12 | B14: =(3*(A14/CONSTR_M)^2-2*(A14/CONSTR_M)^3)-(3*((A14-1)/CONSTR_M)^2-2*((A14-1)/CONSTR_M)^3) -> 0.036222565 | C14: =B14*Capex!$B$9 -> 1.6885871e+08 | D14: =IF(A14>CONSTR_M-6,(FFE+PREOPEN)/6,0) -> 0 | E14: =IF(A14=1,Capex!$B$15,0) -> 0 | F14: =I13 -> 2.6849754e+08 | G14: =F14*RATE/12 -> 4474958.9 | H14: =DEBT_SHARE*(C14+D14+E14+G14) -> 43333416 | I14: =F14+H14 -> 3.1183095e+08
A15: 13 | B15: =(3*(A15/CONSTR_M)^2-2*(A15/CONSTR_M)^3)-(3*((A15-1)/CONSTR_M)^2-2*((A15-1)/CONSTR_M)^3) -> 0.037765775 | C15: =B15*Capex!$B$9 -> 1.7605269e+08 | D15: =IF(A15>CONSTR_M-6,(FFE+PREOPEN)/6,0) -> 0 | E15: =IF(A15=1,Capex!$B$15,0) -> 0 | F15: =I14 -> 3.1183095e+08 | G15: =F15*RATE/12 -> 5197182.5 | H15: =DEBT_SHARE*(C15+D15+E15+G15) -> 45312467 | I15: =F15+H15 -> 3.5714342e+08
... A38: 36 | B38: =(3*(A38/CONSTR_M)^2-2*(A38/CONSTR_M)^3)-(3*((A38-1)/CONSTR_M)^2-2*((A38-1)/CONSTR_M)^3) -> 0.0022719479 | C38: =B38*Capex!$B$9 -> 10591138 | D38: =IF(A38>CONSTR_M-6,(FFE+PREOPEN)/6,0) -> 47170000 | E38: =IF(A38=1,Capex!$B$15,0) -> 0 | F38: =I37 -> 1.3110469e+09 | G38: =F38*RATE/12 -> 21850781 | H38: =DEBT_SHARE*(C38+D38+E38+G38) -> 19902980 | I38: =F38+H38 -> 1.3309499e+09
A39: TOTAL | G39: =SUM(G3:G38) -> 3.6053747e+08 | I39: =I38 -> 1.3309499e+09

Sheet Capex
A1: Development Cost / Capex
A2: Item | B2: ETB | C2: % of capex | D2: Note
A3: Construction works (BOQ A–J) | B3: =BOQ_A+BOQ_B+BOQ_C+BOQ_D+BOQ_E+BOQ_F+BOQ_G+BOQ_H+BOQ_I+BOQ_J -> 4064100000 | C3: =B3/$B$18 -> 0.59297037 | D3: Sum of the 10 BOQ elements
A4: In-house design @2% | B4: =B3*DESIGN_PCT -> 81282000 | C4: =B4/$B$18 -> 0.011859407 | D4: TDOMA staff cost, capitalised per IAS 16.17(a); general overhead excluded per IAS 16.19(d)
A5: Specialist consultancy | B5: =OA12_FEE -> 16849500 | C5: =B5/$B$18 -> 0.0024584174 | D5: Industry norm, not a vendor quotation — specialist systems need external design
A6: Contingency @12% | B6: =(B3+B4+B5)*CONT_PCT -> 499467780 | C6: =B6/$B$18 -> 0.072874584 | D6: On construction + design + specialist
B7: =0 -> 0 | C7: =B7/$B$18 -> 0
A9: Capital works | B9: =B3+B4+B5+B6 -> 4661699280 | C9: =B9/$B$18 -> 0.68016278
A11: FF&E — TDOMA scope | B11: =FFE -> 163020000 | C11: =B11/$B$18 -> 0.023785347 | D11: Common areas + HQ + hire-out venues. Operator fits out hotel; tenants fit out demises.
A12: IDC (IAS 23, capitalised) | B12: =IDC_TOTAL -> 3.6053747e+08 | C12: =B12/$B$18 -> 0.052604029 | D12: SOLVED monthly on the IDC sheet — model is fully ACYCLIC, no iteration needed (see Cover)
B13: =0 -> 0 | C13: =B13/$B$18 -> 0
A15: Arrangement fee @1.5% | B15: =ARR_PCT*DEBT_SHARE*(B9+FFE+PREOPEN) -> 18542697 | C15: =B15/$B$18 -> 0.0027054625 | D15: Borrowing cost — IAS 23
A16: Building sub-total (CASH) | B16: =B9+B11+B12+B15 -> 5.2037994e+09
A17: Land (in-kind, NON-CASH) | B17: =PLOT*LAND_RATE -> 1650000000 | C17: =B17/$B$18 -> 0.24074238
A18: TOTAL CAPEX / DEVELOPMENT COST | B18: =B16+B17 -> 6.8537994e+09 | C18: =B18/$B$18 -> 1
A20: Pre-opening & marketing | B20: =PREOPEN -> 120000000
A21: TOTAL USES | B21: =B18+B20 -> 6.9737994e+09
A23: FUNDING
A24: Cash requirement (ex-land) | B24: =B16+B20 -> 5.3237994e+09
A25: TDOMA equity (75% of cash) | B25: =B24*(1-DEBT_SHARE) -> 3.9928496e+09
A26: City land (in-kind, non-cash) | B26: =B17 -> 1650000000
A27: Debt (25% of cash) | B27: =B24*DEBT_SHARE -> 1.3309499e+09
A28: TOTAL SOURCES | B28: =B25+B26+B27 -> 6.9737994e+09
A29: CHECK: Sources − Uses | B29: =B28-B21 -> 0
A30: Input VAT recoverable on capex (refunded in year 1) | B30: =(CAP_WORKS+FFE)*VAT_R/(1+VAT_R) -> 6.2931121e+08
A31: Memo — USD @160 | B31: =B18/FX -> 42836247
A32: Capex per gross m2 | B32: =B18/(ABOVE_GRADE+BASEMENT_A) -> 181317.45
A33: EFFECTIVE capex per TDOMA gross m2 (70%) | B33: =B18/((ABOVE_GRADE+BASEMENT_A)*0.7) -> 259024.92

Sheet Revenue
A1: Revenue — stabilised & ramped
A2: Operating year | B2: m2 | C2: ETB/m2/mo | D2: Occ % | E2: O1 | F2: O2 | G2: O3 | H2: O4 | I2: O5 | J2: O6 | K2: O7 | L2: O8 | M2: O9 | N2: O10 | O2: O11 | P2: O12
A3: Rent escalation factor | E3: =(1+RENT_ESC)^0 -> 1 | F3: =(1+RENT_ESC)^1 -> 1.25 | G3: =(1+RENT_ESC)^2 -> 1.5625 | H3: =(1+RENT_ESC)^3 -> 1.953125 | I3: =(1+RENT_ESC)^4 -> 2.4414062 | J3: =(1+RENT_ESC)^5 -> 3.0517578 | K3: =(1+RENT_ESC)^6 -> 3.8146973 | L3: =(1+RENT_ESC)^7 -> 4.7683716 | M3: =(1+RENT_ESC)^8 -> 5.9604645 | N3: =(1+RENT_ESC)^9 -> 7.4505806 | O3: =(1+RENT_ESC)^10 -> 9.3132257 | P3: =(1+RENT_ESC)^11 -> 11.641532
A4: Occupancy ramp factor | E4: =IF(1=1,OCC_Y1,IF(1=2,OCC_Y2,OCC_STAB)) -> 0.75 | F4: =IF(2=1,OCC_Y1,IF(2=2,OCC_Y2,OCC_STAB)) -> 0.85 | G4: =IF(3=1,OCC_Y1,IF(3=2,OCC_Y2,OCC_STAB)) -> 0.95 | H4: =IF(4=1,OCC_Y1,IF(4=2,OCC_Y2,OCC_STAB)) -> 0.95 | I4: =IF(5=1,OCC_Y1,IF(5=2,OCC_Y2,OCC_STAB)) -> 0.95 | J4: =IF(6=1,OCC_Y1,IF(6=2,OCC_Y2,OCC_STAB)) -> 0.95 | K4: =IF(7=1,OCC_Y1,IF(7=2,OCC_Y2,OCC_STAB)) -> 0.95 | L4: =IF(8=1,OCC_Y1,IF(8=2,OCC_Y2,OCC_STAB)) -> 0.95 | M4: =IF(9=1,OCC_Y1,IF(9=2,OCC_Y2,OCC_STAB)) -> 0.95 | N4: =IF(10=1,OCC_Y1,IF(10=2,OCC_Y2,OCC_STAB)) -> 0.95 | O4: =IF(11=1,OCC_Y1,IF(11=2,OCC_Y2,OCC_STAB)) -> 0.95 | P4: =IF(12=1,OCC_Y1,IF(12=2,OCC_Y2,OCC_STAB)) -> 0.95
A6: RENTAL INCOME = m2 x rate x 12 x occupancy x ramp x escalation
A7: Retail - retained 25% | B7: =RETAIL_TOT*(1-SOLD_PCT) -> 1040 | C7: =RENT_RETAIL -> 6250 | D7: 0.92 | E7: =$B7*$C7*12*OCC_MULT*E$4*E$3/(1+VAT_R) -> 50869565 | F7: =$B7*$C7*12*OCC_MULT*F$4*F$3/(1+VAT_R) -> 72065217 | G7: =$B7*$C7*12*OCC_MULT*G$4*G$3/(1+VAT_R) -> 1.0067935e+08 | H7: =$B7*$C7*12*OCC_MULT*H$4*H$3/(1+VAT_R) -> 1.2584918e+08 | I7: =$B7*$C7*12*OCC_MULT*I$4*I$3/(1+VAT_R) -> 1.5731148e+08 | J7: =$B7*$C7*12*OCC_MULT*J$4*J$3/(1+VAT_R) -> 1.9663935e+08 | K7: =$B7*$C7*12*OCC_MULT*K$4*K$3/(1+VAT_R) -> 2.4579919e+08 | L7: =$B7*$C7*12*OCC_MULT*L$4*L$3/(1+VAT_R) -> 3.0724899e+08 | ... P7: =$B7*$C7*12*OCC_MULT*P$4*P$3/(1+VAT_R) -> 7.501196e+08
A8: Wholesale showrooms | B8: 2220 | C8: =RENT_WHOLESALE -> 4600 | D8: 0.9 | E8: =$B8*$C8*12*OCC_MULT*E$4*E$3/(1+VAT_R) -> 79920000 | F8: =$B8*$C8*12*OCC_MULT*F$4*F$3/(1+VAT_R) -> 113220000 | G8: =$B8*$C8*12*OCC_MULT*G$4*G$3/(1+VAT_R) -> 158175000 | H8: =$B8*$C8*12*OCC_MULT*H$4*H$3/(1+VAT_R) -> 197718750 | I8: =$B8*$C8*12*OCC_MULT*I$4*I$3/(1+VAT_R) -> 2.4714844e+08 | J8: =$B8*$C8*12*OCC_MULT*J$4*J$3/(1+VAT_R) -> 3.0893555e+08 | K8: =$B8*$C8*12*OCC_MULT*K$4*K$3/(1+VAT_R) -> 3.8616943e+08 | L8: =$B8*$C8*12*OCC_MULT*L$4*L$3/(1+VAT_R) -> 4.8271179e+08 | ... P8: =$B8*$C8*12*OCC_MULT*P$4*P$3/(1+VAT_R) -> 1.1784956e+09
A9: Food hall / F&B | B9: 920 | C9: 4480 | D9: 0.9 | E9: =$B9*$C9*12*OCC_MULT*E$4*E$3/(1+VAT_R) -> 32256000 | F9: =$B9*$C9*12*OCC_MULT*F$4*F$3/(1+VAT_R) -> 45696000 | G9: =$B9*$C9*12*OCC_MULT*G$4*G$3/(1+VAT_R) -> 63840000 | H9: =$B9*$C9*12*OCC_MULT*H$4*H$3/(1+VAT_R) -> 79800000 | I9: =$B9*$C9*12*OCC_MULT*I$4*I$3/(1+VAT_R) -> 99750000 | J9: =$B9*$C9*12*OCC_MULT*J$4*J$3/(1+VAT_R) -> 124687500 | K9: =$B9*$C9*12*OCC_MULT*K$4*K$3/(1+VAT_R) -> 155859375 | L9: =$B9*$C9*12*OCC_MULT*L$4*L$3/(1+VAT_R) -> 1.9482422e+08 | ... P9: =$B9*$C9*12*OCC_MULT*P$4*P$3/(1+VAT_R) -> 4.7564507e+08
A10: Commercial office (L6-L8) | B10: 5264 | C10: =RENT_OFFICE -> 4600 | D10: 0.85 | E10: =$B10*$C10*12*OCC_MULT*E$4*E$3/(1+VAT_R) -> 189504000 | F10: =$B10*$C10*12*OCC_MULT*F$4*F$3/(1+VAT_R) -> 268464000 | G10: =$B10*$C10*12*OCC_MULT*G$4*G$3/(1+VAT_R) -> 375060000 | H10: =$B10*$C10*12*OCC_MULT*H$4*H$3/(1+VAT_R) -> 468825000 | I10: =$B10*$C10*12*OCC_MULT*I$4*I$3/(1+VAT_R) -> 586031250 | J10: =$B10*$C10*12*OCC_MULT*J$4*J$3/(1+VAT_R) -> 7.3253906e+08 | K10: =$B10*$C10*12*OCC_MULT*K$4*K$3/(1+VAT_R) -> 9.1567383e+08 | L10: =$B10*$C10*12*OCC_MULT*L$4*L$3/(1+VAT_R) -> 1.1445923e+09 | ... P10: =$B10*$C10*12*OCC_MULT*P$4*P$3/(1+VAT_R) -> 2.7944148e+09
A11: Trade services (ex one-stop) | B11: 1544 | C11: =RENT_TRADE -> 5625 | D11: 0.85 | E11: =$B11*$C11*12*OCC_MULT*E$4*E$3/(1+VAT_R) -> 67969565 | F11: =$B11*$C11*12*OCC_MULT*F$4*F$3/(1+VAT_R) -> 96290217 | G11: =$B11*$C11*12*OCC_MULT*G$4*G$3/(1+VAT_R) -> 1.345231e+08 | H11: =$B11*$C11*12*OCC_MULT*H$4*H$3/(1+VAT_R) -> 1.6815387e+08 | I11: =$B11*$C11*12*OCC_MULT*I$4*I$3/(1+VAT_R) -> 2.1019234e+08 | J11: =$B11*$C11*12*OCC_MULT*J$4*J$3/(1+VAT_R) -> 2.6274043e+08 | K11: =$B11*$C11*12*OCC_MULT*K$4*K$3/(1+VAT_R) -> 3.2842553e+08 | L11: =$B11*$C11*12*OCC_MULT*L$4*L$3/(1+VAT_R) -> 4.1053191e+08 | ... P11: =$B11*$C11*12*OCC_MULT*P$4*P$3/(1+VAT_R) -> 1.0022752e+09
A12: Rooftop F&B / pavilion | B12: 400 | C12: 4000 | D12: 0.85 | E12: =$B12*$C12*12*OCC_MULT*E$4*E$3/(1+VAT_R) -> 12521739 | F12: =$B12*$C12*12*OCC_MULT*F$4*F$3/(1+VAT_R) -> 17739130 | G12: =$B12*$C12*12*OCC_MULT*G$4*G$3/(1+VAT_R) -> 24782609 | H12: =$B12*$C12*12*OCC_MULT*H$4*H$3/(1+VAT_R) -> 30978261 | I12: =$B12*$C12*12*OCC_MULT*I$4*I$3/(1+VAT_R) -> 38722826 | J12: =$B12*$C12*12*OCC_MULT*J$4*J$3/(1+VAT_R) -> 48403533 | K12: =$B12*$C12*12*OCC_MULT*K$4*K$3/(1+VAT_R) -> 60504416 | L12: =$B12*$C12*12*OCC_MULT*L$4*L$3/(1+VAT_R) -> 75630520 | ... P12: =$B12*$C12*12*OCC_MULT*P$4*P$3/(1+VAT_R) -> 1.8464482e+08
A13: Basement warehouse (B2/B3) | B13: =WAREHOUSE_M2 -> 6000 | C13: =WAREHOUSE_RENT -> 3500 | D13: 0.9 | E13: =$B13*$C13*12*OCC_MULT*E$4*E$3/(1+VAT_R) -> 1.6434783e+08 | F13: =$B13*$C13*12*OCC_MULT*F$4*F$3/(1+VAT_R) -> 2.3282609e+08 | G13: =$B13*$C13*12*OCC_MULT*G$4*G$3/(1+VAT_R) -> 3.2527174e+08 | H13: =$B13*$C13*12*OCC_MULT*H$4*H$3/(1+VAT_R) -> 4.0658967e+08 | I13: =$B13*$C13*12*OCC_MULT*I$4*I$3/(1+VAT_R) -> 5.0823709e+08 | J13: =$B13*$C13*12*OCC_MULT*J$4*J$3/(1+VAT_R) -> 6.3529637e+08 | K13: =$B13*$C13*12*OCC_MULT*K$4*K$3/(1+VAT_R) -> 7.9412046e+08 | L13: =$B13*$C13*12*OCC_MULT*L$4*L$3/(1+VAT_R) -> 9.9265057e+08 | ... P13: =$B13*$C13*12*OCC_MULT*P$4*P$3/(1+VAT_R) -> 2.4234633e+09
A14: Rental subtotal (NET of VAT) | B14: =SUM(B7:B13) -> 17388 | E14: =SUM(E7:E13) -> 5.973887e+08 | F14: =SUM(F7:F13) -> 8.4630065e+08 | G14: =SUM(G7:G13) -> 1.1823318e+09 | H14: =SUM(H7:H13) -> 1.4779147e+09 | I14: =SUM(I7:I13) -> 1.8473934e+09 | J14: =SUM(J7:J13) -> 2.3092418e+09 | K14: =SUM(K7:K13) -> 2.8865522e+09 | L14: =SUM(L7:L13) -> 3.6081903e+09 | ... P14: =SUM(P7:P13) -> 8.8090583e+09
A15: Stabilised rent at O1 prices, NET (no ramp, no escalation) | B15: =SUMPRODUCT(B7:B13,C7:C13)*12*OCC_STAB*OCC_MULT/(1+VAT_R) -> 7.5669235e+08
A17: OTHER REVENUE (all NET of VAT — see the Output VAT memo row below)
A18: Key money (IFRS 16 lease premium - deferred over 10 yrs) | B18: =RETAIL_TOT*(1-SOLD_PCT)*KEY_MONEY -> 0 | E18: =IF(1<=10,$B18/10,0)/(1+VAT_R) -> 0 | F18: =IF(2<=10,$B18/10,0)/(1+VAT_R) -> 0 | G18: =IF(3<=10,$B18/10,0)/(1+VAT_R) -> 0 | H18: =IF(4<=10,$B18/10,0)/(1+VAT_R) -> 0 | I18: =IF(5<=10,$B18/10,0)/(1+VAT_R) -> 0 | J18: =IF(6<=10,$B18/10,0)/(1+VAT_R) -> 0 | K18: =IF(7<=10,$B18/10,0)/(1+VAT_R) -> 0 | L18: =IF(8<=10,$B18/10,0)/(1+VAT_R) -> 0 | M18: =IF(9<=10,$B18/10,0)/(1+VAT_R) -> 0 | N18: =IF(10<=10,$B18/10,0)/(1+VAT_R) -> 0 | O18: =IF(11<=10,$B18/10,0)/(1+VAT_R) -> 0 | P18: =IF(12<=10,$B18/10,0)/(1+VAT_R) -> 0
A19: Retail unit sales (IFRS 15 - point in time, at handover) | B19: =RETAIL_TOT*SOLD_PCT -> 3120 | C19: =SALE_PRICE -> 540000 | E19: =IF(1=1,$B19*$C19,0)/(1+VAT_R) -> 1.4650435e+09 | F19: =IF(2=1,$B19*$C19,0)/(1+VAT_R) -> 0 | G19: =IF(3=1,$B19*$C19,0)/(1+VAT_R) -> 0 | H19: =IF(4=1,$B19*$C19,0)/(1+VAT_R) -> 0 | I19: =IF(5=1,$B19*$C19,0)/(1+VAT_R) -> 0 | J19: =IF(6=1,$B19*$C19,0)/(1+VAT_R) -> 0 | K19: =IF(7=1,$B19*$C19,0)/(1+VAT_R) -> 0 | L19: =IF(8=1,$B19*$C19,0)/(1+VAT_R) -> 0 | M19: =IF(9=1,$B19*$C19,0)/(1+VAT_R) -> 0 | N19: =IF(10=1,$B19*$C19,0)/(1+VAT_R) -> 0 | O19: =IF(11=1,$B19*$C19,0)/(1+VAT_R) -> 0 | P19: =IF(12=1,$B19*$C19,0)/(1+VAT_R) -> 0
A20: Operator hotel revenue (MEMO - the operator's, NOT TDOMA's; GROSS, no VAT extraction here) | B20: =HOTEL_KEYS -> 38 | C20: =ADR -> 12800 | E20: =$B20*$C20*(1+ADR_G)^0*IF(1=1,HOCC1,IF(1=2,HOCC2,HOCC3))*365*(1+FB_UPLIFT) -> 159782400 | F20: =$B20*$C20*(1+ADR_G)^1*IF(2=1,HOCC1,IF(2=2,HOCC2,HOCC3))*365*(1+FB_UPLIFT) -> 199461696 | G20: =$B20*$C20*(1+ADR_G)^2*IF(3=1,HOCC1,IF(3=2,HOCC2,HOCC3))*365*(1+FB_UPLIFT) -> 2.4391316e+08 | H20: =$B20*$C20*(1+ADR_G)^3*IF(4=1,HOCC1,IF(4=2,HOCC2,HOCC3))*365*(1+FB_UPLIFT) -> 2.6098708e+08 | I20: =$B20*$C20*(1+ADR_G)^4*IF(5=1,HOCC1,IF(5=2,HOCC2,HOCC3))*365*(1+FB_UPLIFT) -> 2.7925618e+08 | J20: =$B20*$C20*(1+ADR_G)^5*IF(6=1,HOCC1,IF(6=2,HOCC2,HOCC3))*365*(1+FB_UPLIFT) -> 2.9880411e+08 | K20: =$B20*$C20*(1+ADR_G)^6*IF(7=1,HOCC1,IF(7=2,HOCC2,HOCC3))*365*(1+FB_UPLIFT) -> 3.197204e+08 | L20: =$B20*$C20*(1+ADR_G)^7*IF(8=1,HOCC1,IF(8=2,HOCC2,HOCC3))*365*(1+FB_UPLIFT) -> 3.4210082e+08 | M20: =$B20*$C20*(1+ADR_G)^8*IF(9=1,HOCC1,IF(9=2,HOCC2,HOCC3))*365*(1+FB_UPLIFT) -> 3.6604788e+08 | N20: =$B20*$C20*(1+ADR_G)^9*IF(10=1,HOCC1,IF(10=2,HOCC2,HOCC3))*365*(1+FB_UPLIFT) -> 3.9167123e+08 | O20: =$B20*$C20*(1+ADR_G)^10*IF(11=1,HOCC1,IF(11=2,HOCC2,HOCC3))*365*(1+FB_UPLIFT) -> 4.1908822e+08 | P20: =$B20*$C20*(1+ADR_G)^11*IF(12=1,HOCC1,IF(12=2,HOCC2,HOCC3))*365*(1+FB_UPLIFT) -> 4.484244e+08
A21: Hotel turnover rent (IFRS 16 variable lease payment, NET of VAT) | D21: =TURNOVER -> 0.25 | E21: =E20*$D21/(1+VAT_R) -> 34735304 | F21: =F20*$D21/(1+VAT_R) -> 43361238 | G21: =G20*$D21/(1+VAT_R) -> 53024600 | H21: =H20*$D21/(1+VAT_R) -> 56736322 | I21: =I20*$D21/(1+VAT_R) -> 60707864 | J21: =J20*$D21/(1+VAT_R) -> 64957415 | K21: =K20*$D21/(1+VAT_R) -> 69504434 | L21: =L20*$D21/(1+VAT_R) -> 74369744 | ... P21: =P20*$D21/(1+VAT_R) -> 97483564
A22: Other income (events + parking + vending + service charge), NET of VAT | B22: =OTH_EVENTS+OTH_PARKING+OTH_VEND+OTH_SVC -> 276000000 | E22: =$B22*E$3/(1+VAT_R) -> 240000000 | F22: =$B22*F$3/(1+VAT_R) -> 300000000 | G22: =$B22*G$3/(1+VAT_R) -> 375000000 | H22: =$B22*H$3/(1+VAT_R) -> 468750000 | I22: =$B22*I$3/(1+VAT_R) -> 585937500 | J22: =$B22*J$3/(1+VAT_R) -> 732421875 | K22: =$B22*K$3/(1+VAT_R) -> 9.1552734e+08 | L22: =$B22*L$3/(1+VAT_R) -> 1.1444092e+09 | ... P22: =$B22*P$3/(1+VAT_R) -> 2.7939677e+09
A24: TOTAL REVENUE (net of output VAT — IFRS 15.47) | E24: =E14+E18+E19+E21+E22 -> 2.3371675e+09 | F24: =F14+F18+F19+F21+F22 -> 1.1896619e+09 | G24: =G14+G18+G19+G21+G22 -> 1.6103564e+09 | H24: =H14+H18+H19+H21+H22 -> 2.0034011e+09 | I24: =I14+I18+I19+I21+I22 -> 2.4940388e+09 | J24: =J14+J18+J19+J21+J22 -> 3.1066211e+09 | K24: =K14+K18+K19+K21+K22 -> 3.871584e+09 | L24: =L14+L18+L19+L21+L22 -> 4.8269692e+09 | ... P24: =P14+P18+P19+P21+P22 -> 1.170051e+10
E25: =E24*VAT_R -> 3.5057512e+08 | F25: =F24*VAT_R -> 1.7844928e+08 | G25: =G24*VAT_R -> 2.4155346e+08 | H25: =H24*VAT_R -> 3.0051016e+08 | I25: =I24*VAT_R -> 3.7410582e+08 | J25: =J24*VAT_R -> 4.6599316e+08 | K25: =K24*VAT_R -> 5.807376e+08 | L25: =L24*VAT_R -> 7.2404538e+08 | ... P25: =P24*VAT_R -> 1.7550764e+09

Sheet Opex
A1: Operating Expenses
A3: Operating year | B3: Rate | C3: Driver | E3: O1 | F3: O2 | G3: O3 | H3: O4 | I3: O5 | J3: O6 | K3: O7 | L3: O8 | M3: O9 | N3: O10 | O3: O11 | P3: O12
A4: Opex escalation factor | E4: =(1+OPEX_ESC)^0 -> 1 | F4: =(1+OPEX_ESC)^1 -> 1.05 | G4: =(1+OPEX_ESC)^2 -> 1.1025 | H4: =(1+OPEX_ESC)^3 -> 1.157625 | I4: =(1+OPEX_ESC)^4 -> 1.2155063 | J4: =(1+OPEX_ESC)^5 -> 1.2762816 | K4: =(1+OPEX_ESC)^6 -> 1.3400956 | L4: =(1+OPEX_ESC)^7 -> 1.4071004 | M4: =(1+OPEX_ESC)^8 -> 1.4774554 | N4: =(1+OPEX_ESC)^9 -> 1.5513282 | O4: =(1+OPEX_ESC)^10 -> 1.6288946 | P4: =(1+OPEX_ESC)^11 -> 1.7103394
A6: OPERATING EXPENSES
A7: Property opex (NET of recoverable input VAT) | B7: =PROP_OPEX -> 0.25 | C7: x stabilised rent, escalated, /(1+VAT_R) | E7: =$B7*STAB_RENT*E$4/(1+VAT_R) -> 1.6449834e+08 | F7: =$B7*STAB_RENT*F$4/(1+VAT_R) -> 1.7272325e+08 | G7: =$B7*STAB_RENT*G$4/(1+VAT_R) -> 1.8135942e+08 | H7: =$B7*STAB_RENT*H$4/(1+VAT_R) -> 1.9042739e+08 | I7: =$B7*STAB_RENT*I$4/(1+VAT_R) -> 1.9994876e+08 | J7: =$B7*STAB_RENT*J$4/(1+VAT_R) -> 2.0994619e+08 | K7: =$B7*STAB_RENT*K$4/(1+VAT_R) -> 2.204435e+08 | L7: =$B7*STAB_RENT*L$4/(1+VAT_R) -> 2.3146568e+08 | ... P7: =$B7*STAB_RENT*P$4/(1+VAT_R) -> 2.8134798e+08
A8: Management fee | B8: =MGMT_FEE -> 0.04 | C8: x NET revenue (a computed %, not a quoted gross price -- no VAT extraction) | E8: =$B8*Revenue!E24 -> 93486699 | F8: =$B8*Revenue!F24 -> 47586476 | G8: =$B8*Revenue!G24 -> 64414256 | H8: =$B8*Revenue!H24 -> 80136043 | I8: =$B8*Revenue!I24 -> 99761552 | J8: =$B8*Revenue!J24 -> 1.2426484e+08 | K8: =$B8*Revenue!K24 -> 1.5486336e+08 | L8: =$B8*Revenue!L24 -> 1.9307877e+08 | ... P8: =$B8*Revenue!P24 -> 4.6802038e+08
A9: Bad debt | B9: =BAD_DEBT -> 0.02 | C9: x billed rent; a write-off, not a supply, no VAT | E9: =$B9*Revenue!E14 -> 11947774 | F9: =$B9*Revenue!F14 -> 16926013 | G9: =$B9*Revenue!G14 -> 23646636 | H9: =$B9*Revenue!H14 -> 29558295 | I9: =$B9*Revenue!I14 -> 36947869 | J9: =$B9*Revenue!J14 -> 46184836 | K9: =$B9*Revenue!K14 -> 57731045 | L9: =$B9*Revenue!L14 -> 72163806 | ... P9: =$B9*Revenue!P14 -> 1.7618117e+08
A10: Hotel operating cost | C10: NIL - operator bears it | E10: 0 | F10: 0 | G10: 0 | H10: 0 | I10: 0 | J10: 0 | K10: 0 | L10: 0 | M10: 0 | N10: 0 | O10: 0 | P10: 0
A11: Cloud infrastructure opex (NET of recoverable input VAT) | B11: =CLOUD_OPEX -> 12000000 | C11: replaces on-site data centre; escalated, /(1+VAT_R) | E11: =$B11*E$4/(1+VAT_R) -> 10434783 | F11: =$B11*F$4/(1+VAT_R) -> 10956522 | G11: =$B11*G$4/(1+VAT_R) -> 11504348 | H11: =$B11*H$4/(1+VAT_R) -> 12079565 | I11: =$B11*I$4/(1+VAT_R) -> 12683543 | J11: =$B11*J$4/(1+VAT_R) -> 13317721 | K11: =$B11*K$4/(1+VAT_R) -> 13983607 | L11: =$B11*L$4/(1+VAT_R) -> 14682787 | ... P11: =$B11*P$4/(1+VAT_R) -> 17847019
A12: Property tax | B12: =PROP_TAX -> 0.01 | C12: x market value proxy (ESTIMATE: NOI excl. ptax, capitalised @ exit cap); a levy, no VAT | E12: =$B12*(Revenue!E24-E7-E8-E9-E11)/EXIT_CAP -> 1.958857e+08 | F12: =$B12*(Revenue!F24-F7-F8-F9-F11)/EXIT_CAP -> 89663774 | G12: =$B12*(Revenue!G24-G7-G8-G9-G11)/EXIT_CAP -> 1.2661255e+08 | H12: =$B12*(Revenue!H24-H7-H8-H9-H11)/EXIT_CAP -> 1.6106665e+08 | I12: =$B12*(Revenue!I24-I7-I8-I9-I11)/EXIT_CAP -> 2.0425686e+08 | J12: =$B12*(Revenue!J24-J7-J8-J9-J11)/EXIT_CAP -> 2.5837214e+08 | K12: =$B12*(Revenue!K24-K7-K8-K9-K11)/EXIT_CAP -> 3.2614881e+08 | L12: =$B12*(Revenue!L24-L7-L8-L9-L11)/EXIT_CAP -> 4.1100744e+08 | ... P12: =$B12*(Revenue!P24-P7-P8-P9-P11)/EXIT_CAP -> 1.024487e+09
A13: memo: input VAT recovered (property opex + cloud) | E13: =(E7+E11)*VAT_R -> 26239968 | F13: =(F7+F11)*VAT_R -> 27551966 | G13: =(G7+G11)*VAT_R -> 28929565 | H13: =(H7+H11)*VAT_R -> 30376043 | I13: =(I7+I11)*VAT_R -> 31894845 | J13: =(J7+J11)*VAT_R -> 33489587 | K13: =(K7+K11)*VAT_R -> 35164067 | L13: =(L7+L11)*VAT_R -> 36922270 | ... P13: =(P7+P11)*VAT_R -> 44879250
A14: TOTAL OPEX (net) | E14: =SUM(E7:E12) -> 4.762533e+08 | F14: =SUM(F7:F12) -> 3.3785604e+08 | G14: =SUM(G7:G12) -> 4.075372e+08 | H14: =SUM(H7:H12) -> 4.7326793e+08 | I14: =SUM(I7:I12) -> 5.5359858e+08 | J14: =SUM(J7:J12) -> 6.5208573e+08 | K14: =SUM(K7:K12) -> 7.7317032e+08 | L14: =SUM(L7:L12) -> 9.2239848e+08 | ... P14: =SUM(P7:P12) -> 1.9678835e+09

Sheet Financing
A1: Loan Amortisation & Covenant
A2: Operating year | E2: O1 | F2: O2 | G2: O3 | H2: O4 | I2: O5 | J2: O6 | K2: O7 | L2: O8 | M2: O9 | N2: O10 | O2: O11 | P2: O12
A3: Loan drawn at completion | B3: =DEBT_V -> 1.3309499e+09
A4: Amortisation period (tenor - grace) | B4: =TENOR-GRACE_Y -> 4
A5: Annuity (level debt service) | B5: =$B$3*RATE/(1-(1+RATE)^-$B$4) -> 5.1413145e+08
A7: LOAN SCHEDULE
A8: Opening balance | E8: =$B$3 -> 1.3309499e+09 | F8: =E11 -> 1.0830084e+09 | G8: =F11 -> 7.8547861e+08 | H8: =G11 -> 4.2844288e+08 | I8: =H11 -> 0 | J8: =I11 -> 0 | K8: =J11 -> 0 | L8: =K11 -> 0 | M8: =L11 -> 0 | ... P8: =O11 -> 0
A9: Interest | E9: =IF(1<=$B$4,E8*RATE,0) -> 2.6618997e+08 | F9: =IF(2<=$B$4,F8*RATE,0) -> 2.1660168e+08 | G9: =IF(3<=$B$4,G8*RATE,0) -> 1.5709572e+08 | H9: =IF(4<=$B$4,H8*RATE,0) -> 85688575 | I9: =IF(5<=$B$4,I8*RATE,0) -> 0 | J9: =IF(6<=$B$4,J8*RATE,0) -> 0 | K9: =IF(7<=$B$4,K8*RATE,0) -> 0 | L9: =IF(8<=$B$4,L8*RATE,0) -> 0 | M9: =IF(9<=$B$4,M8*RATE,0) -> 0 | N9: =IF(10<=$B$4,N8*RATE,0) -> 0 | O9: =IF(11<=$B$4,O8*RATE,0) -> 0 | P9: =IF(12<=$B$4,P8*RATE,0) -> 0
A10: Principal | E10: =IF(1<=$B$4,$B$5-E9,0) -> 2.4794148e+08 | F10: =IF(2<=$B$4,$B$5-F9,0) -> 2.9752978e+08 | G10: =IF(3<=$B$4,$B$5-G9,0) -> 3.5703573e+08 | H10: =IF(4<=$B$4,$B$5-H9,0) -> 4.2844288e+08 | I10: =IF(5<=$B$4,$B$5-I9,0) -> 0 | J10: =IF(6<=$B$4,$B$5-J9,0) -> 0 | K10: =IF(7<=$B$4,$B$5-K9,0) -> 0 | L10: =IF(8<=$B$4,$B$5-L9,0) -> 0 | M10: =IF(9<=$B$4,$B$5-M9,0) -> 0 | N10: =IF(10<=$B$4,$B$5-N9,0) -> 0 | O10: =IF(11<=$B$4,$B$5-O9,0) -> 0 | P10: =IF(12<=$B$4,$B$5-P9,0) -> 0
A11: Closing balance | E11: =E8-E10 -> 1.0830084e+09 | F11: =F8-F10 -> 7.8547861e+08 | G11: =G8-G10 -> 4.2844288e+08 | H11: =H8-H10 -> 0 | I11: =I8-I10 -> 0 | J11: =J8-J10 -> 0 | K11: =K8-K10 -> 0 | L11: =L8-L10 -> 0 | ... P11: =P8-P10 -> 0
A12: Debt service | E12: =E9+E10 -> 5.1413145e+08 | F12: =F9+F10 -> 5.1413145e+08 | G12: =G9+G10 -> 5.1413145e+08 | H12: =H9+H10 -> 5.1413145e+08 | I12: =I9+I10 -> 0 | J12: =J9+J10 -> 0 | K12: =K9+K10 -> 0 | L12: =L9+L10 -> 0 | ... P12: =P9+P10 -> 0
A14: COVENANT
A15: CFADS (EBITDA + non-cash COS + key money cash - current tax) | E15: =CashFlow!E23 -> 2.3804871e+09 | F15: =CashFlow!F23 -> 7.2867685e+08 | G15: =CashFlow!G23 -> 9.5401969e+08 | H15: =CashFlow!H23 -> 1.1597055e+09 | I15: =CashFlow!I23 -> 1.4196045e+09 | J15: =CashFlow!J23 -> 1.7781836e+09 | K15: =CashFlow!K23 -> 2.2278684e+09 | L15: =CashFlow!L23 -> 2.7913543e+09 | ... P15: =CashFlow!P23 -> 6.869047e+09
A16: DSCR | E16: =IF(E12=0,"",E15/E12) -> 4.6301137 | F16: =IF(F12=0,"",F15/F12) -> 1.4172968 | G16: =IF(G12=0,"",G15/G12) -> 1.8555949 | H16: =IF(H12=0,"",H15/H12) -> 2.2556596 | I16: =IF(I12=0,"",I15/I12) | J16: =IF(J12=0,"",J15/J12) | K16: =IF(K12=0,"",K15/K12) | L16: =IF(L12=0,"",L15/L12) | ... P16: =IF(P12=0,"",P15/P12)
A17: Covenant test | E17: =IF(E12=0,"n/a",IF(E16>=DSCR_COV,"PASS","BREACH")) -> PASS | F17: =IF(F12=0,"n/a",IF(F16>=DSCR_COV,"PASS","BREACH")) -> PASS | G17: =IF(G12=0,"n/a",IF(G16>=DSCR_COV,"PASS","BREACH")) -> PASS | H17: =IF(H12=0,"n/a",IF(H16>=DSCR_COV,"PASS","BREACH")) -> PASS | I17: =IF(I12=0,"n/a",IF(I16>=DSCR_COV,"PASS","BREACH")) -> n/a | J17: =IF(J12=0,"n/a",IF(J16>=DSCR_COV,"PASS","BREACH")) -> n/a | K17: =IF(K12=0,"n/a",IF(K16>=DSCR_COV,"PASS","BREACH")) -> n/a | L17: =IF(L12=0,"n/a",IF(L16>=DSCR_COV,"PASS","BREACH")) -> n/a | ... P17: =IF(P12=0,"n/a",IF(P16>=DSCR_COV,"PASS","BREACH")) -> n/a

Sheet AssetSplit
A1: Capex allocation
A2: ALLOCATION SHARES
A3: Sold retail share of net GLA | B3: =RETAIL_TOT*SOLD_PCT/NET_GLA -> 0.14854313
A4: Retained share | B4: =1-B3 -> 0.85145687
A5: HQ share of net GLA | B5: =HQ_A/NET_GLA -> 0.041135022
A6: Capex excluding FF&E | B6: =CAPEX-FFE -> 6.6907794e+09
A8: CARRYING AMOUNTS AT COMPLETION (GROSS, before VAT exclusion)
A9: Inventory (IAS 2) - retail units for sale | B9: =$B$3*$B$6 -> 9.9386935e+08
A10: PPE (IAS 16) - TDOMA HQ | B10: =$B$5*$B$6+HQ_A1*HQ_R1+HQ_A2*HQ_R2 -> 2.9946536e+08
A11: Investment property (IAS 40) | B11: =CAPEX-B9-B10 -> 5.5604647e+09
A12: CHECK: sum = total capex | B12: =B9+B10+B11-CAPEX -> 0
A14: RECOVERABLE INPUT VAT — excluded from capitalised cost (IAS 16.16(c), audit V2-08)
A15: Input VAT recoverable on capex | B15: =INPUT_VAT_CAPEX -> 6.2931121e+08
A16: Vatable base for allocation (excl. land) | B16: =B9+B10+B11-LAND_V -> 5.2037994e+09
A18: CARRYING AMOUNTS AT COMPLETION (NET of recoverable VAT)
A19: Inventory (IAS 2), net | B19: =B9-$B$15*(B9/$B$16) -> 8.7367772e+08
A20: PPE (IAS 16), net - TDOMA HQ | B20: =B10-$B$15*(B10/$B$16) -> 2.6325011e+08
A21: Investment property (IAS 40), net | B21: =B11-$B$15*((B11-LAND_V)/$B$16) -> 5.0875604e+09
A22: CHECK: sum = capex − recoverable VAT | B22: =B19+B20+B21-(CAPEX-B15) -> 0
A24: DEPRECIABLE COMPONENTS (retained only, GROSS)
A25: Land - retained share | B25: =LAND_V*$B$4 -> 1.4049038e+09
A26: Specialist systems - retained | B26: =BOQ_I*$B$4 -> 1.3474305e+08
A27: FF&E | B27: =FFE -> 163020000
A28: Building - retained | B28: =(CAPEX-FFE-LAND_V-BOQ_I)*$B$4 -> 4.1572632e+09
A29: Kept-portion vatable base | B29: =B26+B27+B28 -> 4.4550263e+09
A30: VAT attributable to the kept (retained) portion | B30: =$B$15*$B$4 -> 5.3583135e+08
A32: DEPRECIABLE COMPONENTS (retained only, NET of VAT)
A33: Specialist systems - retained, net | B33: =B26-$B$30*(B26/$B$29) -> 1.1853674e+08
A34: FF&E, net | B34: =B27-$B$30*(B27/$B$29) -> 1.4341266e+08
A35: Building - retained, net | B35: =B28-$B$30*(B28/$B$29) -> 3.6572455e+09
A37: Annual depreciation | B37: =B35/LIFE_B+B33/LIFE_S+B34/LIFE_F -> 1.0153488e+08
A39: TAX BASE — two SEPARATE pools (audit TAX-02: a single blended rate is not permitted)
A40: Building tax pool (straight-line) | B40: =B35 -> 3.6572455e+09
A41: Annual tax depreciation - building | B41: =B40*TAX_DEP -> 1.8286228e+08
A42: Plant & machinery tax pool (specialist systems + FF&E) | B42: =B33+B34 -> 2.6194939e+08
A43: Tax depreciation rate - plant & machinery | B43: =TAX_DEP_PLANT -> 0.2
A45: ANNUAL DEPRECIATION SCHEDULE — component-life aware (AUDIT FIX) | E45: O1 | F45: O2 | G45: O3 | H45: O4 | I45: O5 | J45: O6 | K45: O7 | L45: O8 | M45: O9 | N45: O10 | O45: O11 | P45: O12
A47: Year index | E47: =COLUMN()-4 -> 1 | F47: =COLUMN()-4 -> 2 | G47: =COLUMN()-4 -> 3 | H47: =COLUMN()-4 -> 4 | I47: =COLUMN()-4 -> 5 | J47: =COLUMN()-4 -> 6 | K47: =COLUMN()-4 -> 7 | L47: =COLUMN()-4 -> 8 | ... P47: =COLUMN()-4 -> 12
A48: Building depreciation (life 50yr — unaffected) | E48: =$B$35/LIFE_B -> 73144910 | F48: =$B$35/LIFE_B -> 73144910 | G48: =$B$35/LIFE_B -> 73144910 | H48: =$B$35/LIFE_B -> 73144910 | I48: =$B$35/LIFE_B -> 73144910 | J48: =$B$35/LIFE_B -> 73144910 | K48: =$B$35/LIFE_B -> 73144910 | L48: =$B$35/LIFE_B -> 73144910 | ... P48: =$B$35/LIFE_B -> 73144910
A49: Specialist systems depreciation (life 15yr — unaffected) | E49: =$B$33/LIFE_S -> 7902449.1 | F49: =$B$33/LIFE_S -> 7902449.1 | G49: =$B$33/LIFE_S -> 7902449.1 | H49: =$B$33/LIFE_S -> 7902449.1 | I49: =$B$33/LIFE_S -> 7902449.1 | J49: =$B$33/LIFE_S -> 7902449.1 | K49: =$B$33/LIFE_S -> 7902449.1 | L49: =$B$33/LIFE_S -> 7902449.1 | ... P49: =$B$33/LIFE_S -> 7902449.1
A50: FF&E depreciation (life 7yr — CAPPED, was uncapped) | E50: =IF(E47<=LIFE_F,$B$34/LIFE_F,0) -> 20487522 | F50: =IF(F47<=LIFE_F,$B$34/LIFE_F,0) -> 20487522 | G50: =IF(G47<=LIFE_F,$B$34/LIFE_F,0) -> 20487522 | H50: =IF(H47<=LIFE_F,$B$34/LIFE_F,0) -> 20487522 | I50: =IF(I47<=LIFE_F,$B$34/LIFE_F,0) -> 20487522 | J50: =IF(J47<=LIFE_F,$B$34/LIFE_F,0) -> 20487522 | K50: =IF(K47<=LIFE_F,$B$34/LIFE_F,0) -> 20487522 | L50: =IF(L47<=LIFE_F,$B$34/LIFE_F,0) -> 0 | ... P50: =IF(P47<=LIFE_F,$B$34/LIFE_F,0) -> 0
A51: TOTAL ANNUAL DEPRECIATION | E51: =SUM(E48:E50) -> 1.0153488e+08 | F51: =SUM(F48:F50) -> 1.0153488e+08 | G51: =SUM(G48:G50) -> 1.0153488e+08 | H51: =SUM(H48:H50) -> 1.0153488e+08 | I51: =SUM(I48:I50) -> 1.0153488e+08 | J51: =SUM(J48:J50) -> 1.0153488e+08 | K51: =SUM(K48:K50) -> 1.0153488e+08 | L51: =SUM(L48:L50) -> 81047359 | ... P51: =SUM(P48:P50) -> 81047359
A52: Cumulative depreciation to date | E52: =SUM($E$51:E51) -> 1.0153488e+08 | F52: =SUM($E$51:F51) -> 2.0306976e+08 | G52: =SUM($E$51:G51) -> 3.0460465e+08 | H52: =SUM($E$51:H51) -> 4.0613953e+08 | I52: =SUM($E$51:I51) -> 5.0767441e+08 | J52: =SUM($E$51:J51) -> 6.0920929e+08 | K52: =SUM($E$51:K51) -> 7.1074417e+08 | L52: =SUM($E$51:L51) -> 7.9179153e+08 | ... P52: =SUM($E$51:P51) -> 1.115981e+09

Sheet PL
A1: Profit & Loss
A2: Operating year | E2: O1 | F2: O2 | G2: O3 | H2: O4 | I2: O5 | J2: O6 | K2: O7 | L2: O8 | M2: O9 | N2: O10 | O2: O11 | P2: O12
A4: Rental income | E4: =Revenue!E14 -> 5.973887e+08 | F4: =Revenue!F14 -> 8.4630065e+08 | G4: =Revenue!G14 -> 1.1823318e+09 | H4: =Revenue!H14 -> 1.4779147e+09 | I4: =Revenue!I14 -> 1.8473934e+09 | J4: =Revenue!J14 -> 2.3092418e+09 | K4: =Revenue!K14 -> 2.8865522e+09 | L4: =Revenue!L14 -> 3.6081903e+09 | ... P4: =Revenue!P14 -> 8.8090583e+09
A5: Key money (IFRS 16 premium) | E5: =Revenue!E18 -> 0 | F5: =Revenue!F18 -> 0 | G5: =Revenue!G18 -> 0 | H5: =Revenue!H18 -> 0 | I5: =Revenue!I18 -> 0 | J5: =Revenue!J18 -> 0 | K5: =Revenue!K18 -> 0 | L5: =Revenue!L18 -> 0 | ... P5: =Revenue!P18 -> 0
A6: Retail unit sales (IFRS 15) | E6: =Revenue!E19 -> 1.4650435e+09 | F6: =Revenue!F19 -> 0 | G6: =Revenue!G19 -> 0 | H6: =Revenue!H19 -> 0 | I6: =Revenue!I19 -> 0 | J6: =Revenue!J19 -> 0 | K6: =Revenue!K19 -> 0 | L6: =Revenue!L19 -> 0 | ... P6: =Revenue!P19 -> 0
A7: Hotel turnover rent (IFRS 16) | E7: =Revenue!E21 -> 34735304 | F7: =Revenue!F21 -> 43361238 | G7: =Revenue!G21 -> 53024600 | H7: =Revenue!H21 -> 56736322 | I7: =Revenue!I21 -> 60707864 | J7: =Revenue!J21 -> 64957415 | K7: =Revenue!K21 -> 69504434 | L7: =Revenue!L21 -> 74369744 | ... P7: =Revenue!P21 -> 97483564
A8: Other income | E8: =Revenue!E22 -> 240000000 | F8: =Revenue!F22 -> 300000000 | G8: =Revenue!G22 -> 375000000 | H8: =Revenue!H22 -> 468750000 | I8: =Revenue!I22 -> 585937500 | J8: =Revenue!J22 -> 732421875 | K8: =Revenue!K22 -> 9.1552734e+08 | L8: =Revenue!L22 -> 1.1444092e+09 | ... P8: =Revenue!P22 -> 2.7939677e+09
A9: REVENUE | E9: =SUM(E4:E8) -> 2.3371675e+09 | F9: =SUM(F4:F8) -> 1.1896619e+09 | G9: =SUM(G4:G8) -> 1.6103564e+09 | H9: =SUM(H4:H8) -> 2.0034011e+09 | I9: =SUM(I4:I8) -> 2.4940388e+09 | J9: =SUM(J4:J8) -> 3.1066211e+09 | K9: =SUM(K4:K8) -> 3.871584e+09 | L9: =SUM(L4:L8) -> 4.8269692e+09 | ... P9: =SUM(P4:P8) -> 1.170051e+10
A10: Cost of sales (IAS 2) | E10: =IF(1=1,-INVENTORY_V,0) -> -8.7367772e+08 | F10: =IF(2=1,-INVENTORY_V,0) -> 0 | G10: =IF(3=1,-INVENTORY_V,0) -> 0 | H10: =IF(4=1,-INVENTORY_V,0) -> 0 | I10: =IF(5=1,-INVENTORY_V,0) -> 0 | J10: =IF(6=1,-INVENTORY_V,0) -> 0 | K10: =IF(7=1,-INVENTORY_V,0) -> 0 | L10: =IF(8=1,-INVENTORY_V,0) -> 0 | M10: =IF(9=1,-INVENTORY_V,0) -> 0 | N10: =IF(10=1,-INVENTORY_V,0) -> 0 | O10: =IF(11=1,-INVENTORY_V,0) -> 0 | P10: =IF(12=1,-INVENTORY_V,0) -> 0
A11: GROSS PROFIT | E11: =E9+E10 -> 1.4634898e+09 | F11: =F9+F10 -> 1.1896619e+09 | G11: =G9+G10 -> 1.6103564e+09 | H11: =H9+H10 -> 2.0034011e+09 | I11: =I9+I10 -> 2.4940388e+09 | J11: =J9+J10 -> 3.1066211e+09 | K11: =K9+K10 -> 3.871584e+09 | L11: =L9+L10 -> 4.8269692e+09 | ... P11: =P9+P10 -> 1.170051e+10
A12: Operating expenses | E12: =-Opex!E14 -> -4.762533e+08 | F12: =-Opex!F14 -> -3.3785604e+08 | G12: =-Opex!G14 -> -4.075372e+08 | H12: =-Opex!H14 -> -4.7326793e+08 | I12: =-Opex!I14 -> -5.5359858e+08 | J12: =-Opex!J14 -> -6.5208573e+08 | K12: =-Opex!K14 -> -7.7317032e+08 | L12: =-Opex!L14 -> -9.2239848e+08 | ... P12: =-Opex!P14 -> -1.9678835e+09
A13: EBITDA | E13: =E11+E12 -> 9.8723646e+08 | F13: =F11+F12 -> 8.5180585e+08 | G13: =G11+G12 -> 1.2028192e+09 | H13: =H11+H12 -> 1.5301331e+09 | I13: =I11+I12 -> 1.9404402e+09 | J13: =J11+J12 -> 2.4545353e+09 | K13: =K11+K12 -> 3.0984137e+09 | L13: =L11+L12 -> 3.9045707e+09 | ... P13: =P11+P12 -> 9.7326261e+09
A14: Depreciation | E14: =-AssetSplit!E51 -> -1.0153488e+08 | F14: =-AssetSplit!F51 -> -1.0153488e+08 | G14: =-AssetSplit!G51 -> -1.0153488e+08 | H14: =-AssetSplit!H51 -> -1.0153488e+08 | I14: =-AssetSplit!I51 -> -1.0153488e+08 | J14: =-AssetSplit!J51 -> -1.0153488e+08 | K14: =-AssetSplit!K51 -> -1.0153488e+08 | L14: =-AssetSplit!L51 -> -81047359 | ... P14: =-AssetSplit!P51 -> -81047359
A15: EBIT | E15: =E13+E14 -> 8.8570158e+08 | F15: =F13+F14 -> 7.5027097e+08 | G15: =G13+G14 -> 1.1012843e+09 | H15: =H13+H14 -> 1.4285982e+09 | I15: =I13+I14 -> 1.8389053e+09 | J15: =J13+J14 -> 2.3530005e+09 | K15: =K13+K14 -> 2.9968788e+09 | L15: =L13+L14 -> 3.8235234e+09 | ... P15: =P13+P14 -> 9.6515787e+09
A16: Finance cost | E16: =-Financing!E9 -> -2.6618997e+08 | F16: =-Financing!F9 -> -2.1660168e+08 | G16: =-Financing!G9 -> -1.5709572e+08 | H16: =-Financing!H9 -> -85688575 | I16: =-Financing!I9 -> 0 | J16: =-Financing!J9 -> 0 | K16: =-Financing!K9 -> 0 | L16: =-Financing!L9 -> 0 | ... P16: =-Financing!P9 -> 0
A17: PBT | E17: =E15+E16 -> 6.195116e+08 | F17: =F15+F16 -> 5.3366929e+08 | G17: =G15+G16 -> 9.4418859e+08 | H17: =H15+H16 -> 1.3429097e+09 | I17: =I15+I16 -> 1.8389053e+09 | J17: =J15+J16 -> 2.3530005e+09 | K17: =K15+K16 -> 2.9968788e+09 | L17: =L15+L16 -> 3.8235234e+09 | ... P17: =P15+P16 -> 9.6515787e+09
A18: Current tax | E18: =-Tax!E21 -> -1.097383e+08 | F18: =-Tax!F21 -> -1.23129e+08 | G18: =-Tax!G21 -> -2.487995e+08 | H18: =-Tax!H21 -> -3.704276e+08 | I18: =-Tax!I21 -> -5.2083571e+08 | J18: =-Tax!J21 -> -6.7635178e+08 | K18: =-Tax!K21 -> -8.7054531e+08 | L18: =-Tax!L21 -> -1.1132164e+09 | ... P18: =-Tax!P21 -> -2.8635791e+09
A19: Deferred tax | E19: =-Tax!E30 -> -4.6959986e+08 | F19: =-Tax!F30 -> -36971789 | G19: =-Tax!G30 -> -34457075 | H19: =-Tax!H30 -> -32445304 | I19: =-Tax!I30 -> -30835887 | J19: =-Tax!J30 -> -29548353 | K19: =-Tax!K30 -> -28518326 | L19: =-Tax!L30 -> -33840561 | ... P19: =-Tax!P30 -> -31894552
A20: Undistributed-profits tax (15%, on profit retained) | E20: =-Tax!E34 -> 0 | F20: =-Tax!F34 -> 0 | G20: =-Tax!G34 -> 0 | H20: =-Tax!H34 -> 0 | I20: =-Tax!I34 -> 0 | J20: =-Tax!J34 -> 0 | K20: =-Tax!K34 -> 0 | L20: =-Tax!L34 -> 0 | ... P20: =-Tax!P34 -> 0
A21: PAT | E21: =E17+E18+E19+E20 -> 40173444 | F21: =F17+F18+F19+F20 -> 3.7356851e+08 | G21: =G17+G18+G19+G20 -> 6.6093201e+08 | H21: =H17+H18+H19+H20 -> 9.4003677e+08 | I21: =I17+I18+I19+I20 -> 1.2872337e+09 | J21: =J17+J18+J19+J20 -> 1.6471003e+09 | K21: =K17+K18+K19+K20 -> 2.0978152e+09 | L21: =L17+L18+L19+L20 -> 2.6764664e+09 | ... P21: =P17+P18+P19+P20 -> 6.7561051e+09

Sheet Tax
A1: Tax Computation - current & deferred (IAS 12)
A2: Operating year | E2: O1 | F2: O2 | G2: O3 | H2: O4 | I2: O5 | J2: O6 | K2: O7 | L2: O8 | M2: O9 | N2: O10 | O2: O11 | P2: O12
A4: PBT (from P&L) | E4: =PL!E17 -> 6.195116e+08 | F4: =PL!F17 -> 5.3366929e+08 | G4: =PL!G17 -> 9.4418859e+08 | H4: =PL!H17 -> 1.3429097e+09 | I4: =PL!I17 -> 1.8389053e+09 | J4: =PL!J17 -> 2.3530005e+09 | K4: =PL!K17 -> 2.9968788e+09 | L4: =PL!L17 -> 3.8235234e+09 | ... P4: =PL!P17 -> 9.6515787e+09
A5: Add back: accounting depreciation | E5: =-PL!E14 -> 1.0153488e+08 | F5: =-PL!F14 -> 1.0153488e+08 | G5: =-PL!G14 -> 1.0153488e+08 | H5: =-PL!H14 -> 1.0153488e+08 | I5: =-PL!I14 -> 1.0153488e+08 | J5: =-PL!J14 -> 1.0153488e+08 | K5: =-PL!K14 -> 1.0153488e+08 | L5: =-PL!L14 -> 81047359 | ... P5: =-PL!P14 -> 81047359
A6: Less: tax depreciation - building pool (straight-line) | E6: =-MIN(TAX_DEP_AN_BLDG,MAX(TAX_BASE_BLDG-TAX_DEP_AN_BLDG*0,0)) -> -1.8286228e+08 | F6: =-MIN(TAX_DEP_AN_BLDG,MAX(TAX_BASE_BLDG-TAX_DEP_AN_BLDG*1,0)) -> -1.8286228e+08 | G6: =-MIN(TAX_DEP_AN_BLDG,MAX(TAX_BASE_BLDG-TAX_DEP_AN_BLDG*2,0)) -> -1.8286228e+08 | H6: =-MIN(TAX_DEP_AN_BLDG,MAX(TAX_BASE_BLDG-TAX_DEP_AN_BLDG*3,0)) -> -1.8286228e+08 | I6: =-MIN(TAX_DEP_AN_BLDG,MAX(TAX_BASE_BLDG-TAX_DEP_AN_BLDG*4,0)) -> -1.8286228e+08 | J6: =-MIN(TAX_DEP_AN_BLDG,MAX(TAX_BASE_BLDG-TAX_DEP_AN_BLDG*5,0)) -> -1.8286228e+08 | K6: =-MIN(TAX_DEP_AN_BLDG,MAX(TAX_BASE_BLDG-TAX_DEP_AN_BLDG*6,0)) -> -1.8286228e+08 | L6: =-MIN(TAX_DEP_AN_BLDG,MAX(TAX_BASE_BLDG-TAX_DEP_AN_BLDG*7,0)) -> -1.8286228e+08 | M6: =-MIN(TAX_DEP_AN_BLDG,MAX(TAX_BASE_BLDG-TAX_DEP_AN_BLDG*8,0)) -> -1.8286228e+08 | N6: =-MIN(TAX_DEP_AN_BLDG,MAX(TAX_BASE_BLDG-TAX_DEP_AN_BLDG*9,0)) -> -1.8286228e+08 | O6: =-MIN(TAX_DEP_AN_BLDG,MAX(TAX_BASE_BLDG-TAX_DEP_AN_BLDG*10,0)) -> -1.8286228e+08 | P6: =-MIN(TAX_DEP_AN_BLDG,MAX(TAX_BASE_BLDG-TAX_DEP_AN_BLDG*11,0)) -> -1.8286228e+08
A7: Less: tax depreciation - plant & machinery pool (diminishing value) | E7: =-TAX_BASE_PLANT*(1-TAX_DEP_PLANT)^0*TAX_DEP_PLANT -> -52389879 | F7: =-TAX_BASE_PLANT*(1-TAX_DEP_PLANT)^1*TAX_DEP_PLANT -> -41911903 | G7: =-TAX_BASE_PLANT*(1-TAX_DEP_PLANT)^2*TAX_DEP_PLANT -> -33529522 | H7: =-TAX_BASE_PLANT*(1-TAX_DEP_PLANT)^3*TAX_DEP_PLANT -> -26823618 | I7: =-TAX_BASE_PLANT*(1-TAX_DEP_PLANT)^4*TAX_DEP_PLANT -> -21458894 | J7: =-TAX_BASE_PLANT*(1-TAX_DEP_PLANT)^5*TAX_DEP_PLANT -> -17167115 | K7: =-TAX_BASE_PLANT*(1-TAX_DEP_PLANT)^6*TAX_DEP_PLANT -> -13733692 | L7: =-TAX_BASE_PLANT*(1-TAX_DEP_PLANT)^7*TAX_DEP_PLANT -> -10986954 | M7: =-TAX_BASE_PLANT*(1-TAX_DEP_PLANT)^8*TAX_DEP_PLANT -> -8789563.1 | N7: =-TAX_BASE_PLANT*(1-TAX_DEP_PLANT)^9*TAX_DEP_PLANT -> -7031650.5 | O7: =-TAX_BASE_PLANT*(1-TAX_DEP_PLANT)^10*TAX_DEP_PLANT -> -5625320.4 | P7: =-TAX_BASE_PLANT*(1-TAX_DEP_PLANT)^11*TAX_DEP_PLANT -> -4500256.3
A8: Less: tax depreciation (total) | E8: =E6+E7 -> -2.3525215e+08 | F8: =F6+F7 -> -2.2477418e+08 | G8: =G6+G7 -> -2.163918e+08 | H8: =H6+H7 -> -2.0968589e+08 | I8: =I6+I7 -> -2.0432117e+08 | J8: =J6+J7 -> -2.0002939e+08 | K8: =K6+K7 -> -1.9659597e+08 | L8: =L6+L7 -> -1.9384923e+08 | ... P8: =P6+P7 -> -1.8736253e+08
A9: Taxable profit before losses | E9: =E4+E5+E8 -> 4.8579433e+08 | F9: =F4+F5+F8 -> 4.1043e+08 | G9: =G4+G5+G8 -> 8.2933167e+08 | H9: =H4+H5+H8 -> 1.2347587e+09 | I9: =I4+I5+I8 -> 1.736119e+09 | J9: =J4+J5+J8 -> 2.2545059e+09 | K9: =K4+K5+K8 -> 2.9018177e+09 | L9: =L4+L5+L8 -> 3.7107215e+09 | ... P9: =P4+P5+P8 -> 9.5452636e+09
A10: New loss originated this year | E10: =MAX(-E9,0) -> 0 | F10: =MAX(-F9,0) -> 0 | G10: =MAX(-G9,0) -> 0 | H10: =MAX(-H9,0) -> 0 | I10: =MAX(-I9,0) -> 0 | J10: =MAX(-J9,0) -> 0 | K10: =MAX(-K9,0) -> 0 | L10: =MAX(-L9,0) -> 0 | ... P10: =MAX(-P9,0) -> 0
A11: Capacity available before any carried loss | E11: =MAX(E9,0) -> 4.8579433e+08 | F11: =MAX(F9,0) -> 4.1043e+08 | G11: =MAX(G9,0) -> 8.2933167e+08 | H11: =MAX(H9,0) -> 1.2347587e+09 | I11: =MAX(I9,0) -> 1.736119e+09 | J11: =MAX(J9,0) -> 2.2545059e+09 | K11: =MAX(K9,0) -> 2.9018177e+09 | L11: =MAX(L9,0) -> 3.7107215e+09 | ... P11: =MAX(P9,0) -> 9.5452636e+09
A12: Loss bucket, age 1yr - closing balance | E12: =(PREOPEN)-MIN(PREOPEN,E15) -> 0 | F12: =(E10)-MIN(E10,F15) -> 0 | G12: =(F10)-MIN(F10,G15) -> 0 | H12: =(G10)-MIN(G10,H15) -> 0 | I12: =(H10)-MIN(H10,I15) -> 0 | J12: =(I10)-MIN(I10,J15) -> 0 | K12: =(J10)-MIN(J10,K15) -> 0 | L12: =(K10)-MIN(K10,L15) -> 0 | M12: =(L10)-MIN(L10,M15) -> 0 | ... P12: =(O10)-MIN(O10,P15) -> 0
A13: Capacity remaining after using age 1yr bucket | E13: =E15-((PREOPEN)-E12) -> 3.6579433e+08 | F13: =F15-((E10)-F12) -> 4.1043e+08 | G13: =G15-((F10)-G12) -> 8.2933167e+08 | H13: =H15-((G10)-H12) -> 1.2347587e+09 | I13: =I15-((H10)-I12) -> 1.736119e+09 | J13: =J15-((I10)-J12) -> 2.2545059e+09 | K13: =K15-((J10)-K12) -> 2.9018177e+09 | L13: =L15-((K10)-L12) -> 3.7107215e+09 | M13: =M15-((L10)-M12) -> 4.7219755e+09 | ... P13: =P15-((O10)-P12) -> 9.5452636e+09
A14: Loss bucket, age 2yr - closing balance | E14: =(0)-MIN(0,E17) -> 0 | F14: =(E12)-MIN(E12,F17) -> 0 | G14: =(F12)-MIN(F12,G17) -> 0 | H14: =(G12)-MIN(G12,H17) -> 0 | I14: =(H12)-MIN(H12,I17) -> 0 | J14: =(I12)-MIN(I12,J17) -> 0 | K14: =(J12)-MIN(J12,K17) -> 0 | L14: =(K12)-MIN(K12,L17) -> 0 | M14: =(L12)-MIN(L12,M17) -> 0 | ... P14: =(O12)-MIN(O12,P17) -> 0
A15: Capacity remaining after using age 2yr bucket | E15: =E17-((0)-E14) -> 4.8579433e+08 | F15: =F17-((E12)-F14) -> 4.1043e+08 | G15: =G17-((F12)-G14) -> 8.2933167e+08 | H15: =H17-((G12)-H14) -> 1.2347587e+09 | I15: =I17-((H12)-I14) -> 1.736119e+09 | J15: =J17-((I12)-J14) -> 2.2545059e+09 | K15: =K17-((J12)-K14) -> 2.9018177e+09 | L15: =L17-((K12)-L14) -> 3.7107215e+09 | M15: =M17-((L12)-M14) -> 4.7219755e+09 | ... P15: =P17-((O12)-P14) -> 9.5452636e+09
A16: Loss bucket, age 3yr - closing balance | E16: =(0)-MIN(0,E19) -> 0 | F16: =(E14)-MIN(E14,F19) -> 0 | G16: =(F14)-MIN(F14,G19) -> 0 | H16: =(G14)-MIN(G14,H19) -> 0 | I16: =(H14)-MIN(H14,I19) -> 0 | J16: =(I14)-MIN(I14,J19) -> 0 | K16: =(J14)-MIN(J14,K19) -> 0 | L16: =(K14)-MIN(K14,L19) -> 0 | M16: =(L14)-MIN(L14,M19) -> 0 | ... P16: =(O14)-MIN(O14,P19) -> 0
A17: Capacity remaining after using age 3yr bucket | E17: =E19-((0)-E16) -> 4.8579433e+08 | F17: =F19-((E14)-F16) -> 4.1043e+08 | G17: =G19-((F14)-G16) -> 8.2933167e+08 | H17: =H19-((G14)-H16) -> 1.2347587e+09 | I17: =I19-((H14)-I16) -> 1.736119e+09 | J17: =J19-((I14)-J16) -> 2.2545059e+09 | K17: =K19-((J14)-K16) -> 2.9018177e+09 | L17: =L19-((K14)-L16) -> 3.7107215e+09 | M17: =M19-((L14)-M16) -> 4.7219755e+09 | ... P17: =P19-((O14)-P16) -> 9.5452636e+09
A18: Loss bucket, age 4yr - closing balance | E18: =(0)-MIN(0,E11) -> 0 | F18: =(E16)-MIN(E16,F11) -> 0 | G18: =(F16)-MIN(F16,G11) -> 0 | H18: =(G16)-MIN(G16,H11) -> 0 | I18: =(H16)-MIN(H16,I11) -> 0 | J18: =(I16)-MIN(I16,J11) -> 0 | K18: =(J16)-MIN(J16,K11) -> 0 | L18: =(K16)-MIN(K16,L11) -> 0 | M18: =(L16)-MIN(L16,M11) -> 0 | ... P18: =(O16)-MIN(O16,P11) -> 0
A19: Capacity remaining after using age 4yr bucket | E19: =E11-((0)-E18) -> 4.8579433e+08 | F19: =F11-((E16)-F18) -> 4.1043e+08 | G19: =G11-((F16)-G18) -> 8.2933167e+08 | H19: =H11-((G16)-H18) -> 1.2347587e+09 | I19: =I11-((H16)-I18) -> 1.736119e+09 | J19: =J11-((I16)-J18) -> 2.2545059e+09 | K19: =K11-((J16)-K18) -> 2.9018177e+09 | L19: =L11-((K16)-L18) -> 3.7107215e+09 | M19: =M11-((L16)-M18) -> 4.7219755e+09 | ... P19: =P11-((O16)-P18) -> 9.5452636e+09
A20: Taxable profit | E20: =MAX(E13,0) -> 3.6579433e+08 | F20: =MAX(F13,0) -> 4.1043e+08 | G20: =MAX(G13,0) -> 8.2933167e+08 | H20: =MAX(H13,0) -> 1.2347587e+09 | I20: =MAX(I13,0) -> 1.736119e+09 | J20: =MAX(J13,0) -> 2.2545059e+09 | K20: =MAX(K13,0) -> 2.9018177e+09 | L20: =MAX(L13,0) -> 3.7107215e+09 | ... P20: =MAX(P13,0) -> 9.5452636e+09
A21: CURRENT TAX @30% | E21: =E20*CIT -> 1.097383e+08 | F21: =F20*CIT -> 1.23129e+08 | G21: =G20*CIT -> 2.487995e+08 | H21: =H20*CIT -> 3.704276e+08 | I21: =I20*CIT -> 5.2083571e+08 | J21: =J20*CIT -> 6.7635178e+08 | K21: =K20*CIT -> 8.7054531e+08 | L21: =L20*CIT -> 1.1132164e+09 | ... P21: =P20*CIT -> 2.8635791e+09
A23: DEFERRED TAX (IAS 12)
A24: Accounting NBV (IP + PPE) | E24: =MAX(IP_V+PPE_V-AssetSplit!E52,0) -> 5.2492756e+09 | F24: =MAX(IP_V+PPE_V-AssetSplit!F52,0) -> 5.1477407e+09 | G24: =MAX(IP_V+PPE_V-AssetSplit!G52,0) -> 5.0462059e+09 | H24: =MAX(IP_V+PPE_V-AssetSplit!H52,0) -> 4.944671e+09 | I24: =MAX(IP_V+PPE_V-AssetSplit!I52,0) -> 4.8431361e+09 | J24: =MAX(IP_V+PPE_V-AssetSplit!J52,0) -> 4.7416012e+09 | K24: =MAX(IP_V+PPE_V-AssetSplit!K52,0) -> 4.6400663e+09 | L24: =MAX(IP_V+PPE_V-AssetSplit!L52,0) -> 4.559019e+09 | ... P24: =MAX(IP_V+PPE_V-AssetSplit!P52,0) -> 4.2348295e+09
A25: Tax WDV - building pool | E25: =MAX(TAX_BASE_BLDG-TAX_DEP_AN_BLDG*1,0) -> 3.4743832e+09 | F25: =MAX(TAX_BASE_BLDG-TAX_DEP_AN_BLDG*2,0) -> 3.291521e+09 | G25: =MAX(TAX_BASE_BLDG-TAX_DEP_AN_BLDG*3,0) -> 3.1086587e+09 | H25: =MAX(TAX_BASE_BLDG-TAX_DEP_AN_BLDG*4,0) -> 2.9257964e+09 | I25: =MAX(TAX_BASE_BLDG-TAX_DEP_AN_BLDG*5,0) -> 2.7429341e+09 | J25: =MAX(TAX_BASE_BLDG-TAX_DEP_AN_BLDG*6,0) -> 2.5600719e+09 | K25: =MAX(TAX_BASE_BLDG-TAX_DEP_AN_BLDG*7,0) -> 2.3772096e+09 | L25: =MAX(TAX_BASE_BLDG-TAX_DEP_AN_BLDG*8,0) -> 2.1943473e+09 | M25: =MAX(TAX_BASE_BLDG-TAX_DEP_AN_BLDG*9,0) -> 2.011485e+09 | N25: =MAX(TAX_BASE_BLDG-TAX_DEP_AN_BLDG*10,0) -> 1.8286228e+09 | O25: =MAX(TAX_BASE_BLDG-TAX_DEP_AN_BLDG*11,0) -> 1.6457605e+09 | P25: =MAX(TAX_BASE_BLDG-TAX_DEP_AN_BLDG*12,0) -> 1.4628982e+09
A26: Tax WDV - plant & machinery pool | E26: =TAX_BASE_PLANT*(1-TAX_DEP_PLANT)^1 -> 2.0955951e+08 | F26: =TAX_BASE_PLANT*(1-TAX_DEP_PLANT)^2 -> 1.6764761e+08 | G26: =TAX_BASE_PLANT*(1-TAX_DEP_PLANT)^3 -> 1.3411809e+08 | H26: =TAX_BASE_PLANT*(1-TAX_DEP_PLANT)^4 -> 1.0729447e+08 | I26: =TAX_BASE_PLANT*(1-TAX_DEP_PLANT)^5 -> 85835577 | J26: =TAX_BASE_PLANT*(1-TAX_DEP_PLANT)^6 -> 68668462 | K26: =TAX_BASE_PLANT*(1-TAX_DEP_PLANT)^7 -> 54934769 | L26: =TAX_BASE_PLANT*(1-TAX_DEP_PLANT)^8 -> 43947816 | M26: =TAX_BASE_PLANT*(1-TAX_DEP_PLANT)^9 -> 35158252 | N26: =TAX_BASE_PLANT*(1-TAX_DEP_PLANT)^10 -> 28126602 | O26: =TAX_BASE_PLANT*(1-TAX_DEP_PLANT)^11 -> 22501282 | P26: =TAX_BASE_PLANT*(1-TAX_DEP_PLANT)^12 -> 18001025
A27: Tax written-down value (total) | E27: =E25+E26 -> 3.6839428e+09 | F27: =F25+F26 -> 3.4591686e+09 | G27: =G25+G26 -> 3.2427768e+09 | H27: =H25+H26 -> 3.0330909e+09 | I27: =I25+I26 -> 2.8287697e+09 | J27: =J25+J26 -> 2.6287403e+09 | K27: =K25+K26 -> 2.4321444e+09 | L27: =L25+L26 -> 2.2382951e+09 | ... P27: =P25+P26 -> 1.4808992e+09
A28: Temporary difference | E28: =E24-E27 -> 1.5653329e+09 | F28: =F24-F27 -> 1.6885722e+09 | G28: =G24-G27 -> 1.8034291e+09 | H28: =H24-H27 -> 1.9115801e+09 | I28: =I24-I27 -> 2.0143664e+09 | J28: =J24-J27 -> 2.1128609e+09 | K28: =K24-K27 -> 2.207922e+09 | L28: =L24-L27 -> 2.3207238e+09 | ... P28: =P24-P27 -> 2.7539303e+09
A29: Deferred tax liability (closing) | E29: =MAX(E28,0)*CIT -> 4.6959986e+08 | F29: =MAX(F28,0)*CIT -> 5.0657165e+08 | G29: =MAX(G28,0)*CIT -> 5.4102872e+08 | H29: =MAX(H28,0)*CIT -> 5.7347403e+08 | I29: =MAX(I28,0)*CIT -> 6.0430991e+08 | J29: =MAX(J28,0)*CIT -> 6.3385827e+08 | K29: =MAX(K28,0)*CIT -> 6.6237659e+08 | L29: =MAX(L28,0)*CIT -> 6.9621715e+08 | ... P29: =MAX(P28,0)*CIT -> 8.2617909e+08
A30: DEFERRED TAX CHARGE (movement) | E30: =E29 -> 4.6959986e+08 | F30: =F29-E29 -> 36971789 | G30: =G29-F29 -> 34457075 | H30: =H29-G29 -> 32445304 | I30: =I29-H29 -> 30835887 | J30: =J29-I29 -> 29548353 | K30: =K29-J29 -> 28518326 | L30: =L29-K29 -> 33840561 | M30: =M29-L29 -> 33181344 | ... P30: =P29-O29 -> 31894552
A32: UNDISTRIBUTED-PROFITS TAX (Proc. 1395/2025)
A33: Profit before undistributed-profits tax | E33: =E4-E21-E30 -> 40173444 | F33: =F4-F21-F30 -> 3.7356851e+08 | G33: =G4-G21-G30 -> 6.6093201e+08 | H33: =H4-H21-H30 -> 9.4003677e+08 | I33: =I4-I21-I30 -> 1.2872337e+09 | J33: =J4-J21-J30 -> 1.6471003e+09 | K33: =K4-K21-K30 -> 2.0978152e+09 | L33: =L4-L21-L30 -> 2.6764664e+09 | ... P33: =P4-P21-P30 -> 6.7561051e+09
A34: Undistributed-profits tax (15%, on profit retained) | C34: Closed form: div=payout*PAT and undist_tax=(PAT-div)*rate both depend on PAT, but solving algebraically avoids any circularity -- year 1 has payout=0 (no dividend yet), so 100% of year-1 profit is 'retained' for this purpose. | E34: =E33*(1-0)*UNDIST_TAX_RATE/(1+(1-0)*UNDIST_TAX_RATE) -> 0 | F34: =F33*(1-PAYOUT)*UNDIST_TAX_RATE/(1+(1-PAYOUT)*UNDIST_TAX_RATE) -> 0 | G34: =G33*(1-PAYOUT)*UNDIST_TAX_RATE/(1+(1-PAYOUT)*UNDIST_TAX_RATE) -> 0 | H34: =H33*(1-PAYOUT)*UNDIST_TAX_RATE/(1+(1-PAYOUT)*UNDIST_TAX_RATE) -> 0 | I34: =I33*(1-PAYOUT)*UNDIST_TAX_RATE/(1+(1-PAYOUT)*UNDIST_TAX_RATE) -> 0 | J34: =J33*(1-PAYOUT)*UNDIST_TAX_RATE/(1+(1-PAYOUT)*UNDIST_TAX_RATE) -> 0 | K34: =K33*(1-PAYOUT)*UNDIST_TAX_RATE/(1+(1-PAYOUT)*UNDIST_TAX_RATE) -> 0 | L34: =L33*(1-PAYOUT)*UNDIST_TAX_RATE/(1+(1-PAYOUT)*UNDIST_TAX_RATE) -> 0 | M34: =M33*(1-PAYOUT)*UNDIST_TAX_RATE/(1+(1-PAYOUT)*UNDIST_TAX_RATE) -> 0 | ... P34: =P33*(1-PAYOUT)*UNDIST_TAX_RATE/(1+(1-PAYOUT)*UNDIST_TAX_RATE) -> 0

Sheet CashFlow
A1: Cash Flow Statement (IAS 7)
A2: Operating year | E2: O1 | F2: O2 | G2: O3 | H2: O4 | I2: O5 | J2: O6 | K2: O7 | L2: O8 | M2: O9 | N2: O10 | O2: O11 | P2: O12
A3: OPERATING
A4: EBITDA | E4: =PL!E13 -> 9.8723646e+08 | F4: =PL!F13 -> 8.5180585e+08 | G4: =PL!G13 -> 1.2028192e+09 | H4: =PL!H13 -> 1.5301331e+09 | I4: =PL!I13 -> 1.9404402e+09 | J4: =PL!J13 -> 2.4545353e+09 | K4: =PL!K13 -> 3.0984137e+09 | L4: =PL!L13 -> 3.9045707e+09 | ... P4: =PL!P13 -> 9.7326261e+09
A5: Add back non-cash cost of sales | E5: =-PL!E10 -> 8.7367772e+08 | F5: =-PL!F10 -> 0 | G5: =-PL!G10 -> 0 | H5: =-PL!H10 -> 0 | I5: =-PL!I10 -> 0 | J5: =-PL!J10 -> 0 | K5: =-PL!K10 -> 0 | L5: =-PL!L10 -> 0 | ... P5: =-PL!P10 -> 0
A6: Key money received (cash, at inception) | E6: =IF(1=1,RETAIL_TOT*(1-SOLD_PCT)*KEY_MONEY,0) -> 0 | F6: =IF(2=1,RETAIL_TOT*(1-SOLD_PCT)*KEY_MONEY,0) -> 0 | G6: =IF(3=1,RETAIL_TOT*(1-SOLD_PCT)*KEY_MONEY,0) -> 0 | H6: =IF(4=1,RETAIL_TOT*(1-SOLD_PCT)*KEY_MONEY,0) -> 0 | I6: =IF(5=1,RETAIL_TOT*(1-SOLD_PCT)*KEY_MONEY,0) -> 0 | J6: =IF(6=1,RETAIL_TOT*(1-SOLD_PCT)*KEY_MONEY,0) -> 0 | K6: =IF(7=1,RETAIL_TOT*(1-SOLD_PCT)*KEY_MONEY,0) -> 0 | L6: =IF(8=1,RETAIL_TOT*(1-SOLD_PCT)*KEY_MONEY,0) -> 0 | M6: =IF(9=1,RETAIL_TOT*(1-SOLD_PCT)*KEY_MONEY,0) -> 0 | N6: =IF(10=1,RETAIL_TOT*(1-SOLD_PCT)*KEY_MONEY,0) -> 0 | O6: =IF(11=1,RETAIL_TOT*(1-SOLD_PCT)*KEY_MONEY,0) -> 0 | P6: =IF(12=1,RETAIL_TOT*(1-SOLD_PCT)*KEY_MONEY,0) -> 0
A7: Less key money recognised in revenue | E7: =-PL!E5 -> 0 | F7: =-PL!F5 -> 0 | G7: =-PL!G5 -> 0 | H7: =-PL!H5 -> 0 | I7: =-PL!I5 -> 0 | J7: =-PL!J5 -> 0 | K7: =-PL!K5 -> 0 | L7: =-PL!L5 -> 0 | ... P7: =-PL!P5 -> 0
A8: Current tax paid | E8: =PL!E18 -> -1.097383e+08 | F8: =PL!F18 -> -1.23129e+08 | G8: =PL!G18 -> -2.487995e+08 | H8: =PL!H18 -> -3.704276e+08 | I8: =PL!I18 -> -5.2083571e+08 | J8: =PL!J18 -> -6.7635178e+08 | K8: =PL!K18 -> -8.7054531e+08 | L8: =PL!L18 -> -1.1132164e+09 | ... P8: =PL!P18 -> -2.8635791e+09
A9: Undistributed-profits tax paid | E9: =PL!E20 -> 0 | F9: =PL!F20 -> 0 | G9: =PL!G20 -> 0 | H9: =PL!H20 -> 0 | I9: =PL!I20 -> 0 | J9: =PL!J20 -> 0 | K9: =PL!K20 -> 0 | L9: =PL!L20 -> 0 | ... P9: =PL!P20 -> 0
A10: Input VAT refund on capex (O1 only) | E10: =IF(1=1,INPUT_VAT_CAPEX,0) -> 6.2931121e+08 | F10: =IF(2=1,INPUT_VAT_CAPEX,0) -> 0 | G10: =IF(3=1,INPUT_VAT_CAPEX,0) -> 0 | H10: =IF(4=1,INPUT_VAT_CAPEX,0) -> 0 | I10: =IF(5=1,INPUT_VAT_CAPEX,0) -> 0 | J10: =IF(6=1,INPUT_VAT_CAPEX,0) -> 0 | K10: =IF(7=1,INPUT_VAT_CAPEX,0) -> 0 | L10: =IF(8=1,INPUT_VAT_CAPEX,0) -> 0 | M10: =IF(9=1,INPUT_VAT_CAPEX,0) -> 0 | N10: =IF(10=1,INPUT_VAT_CAPEX,0) -> 0 | O10: =IF(11=1,INPUT_VAT_CAPEX,0) -> 0 | P10: =IF(12=1,INPUT_VAT_CAPEX,0) -> 0
A11: NET OPERATING CASH FLOW | E11: =SUM(E4:E10) -> 2.3804871e+09 | F11: =SUM(F4:F10) -> 7.2867685e+08 | G11: =SUM(G4:G10) -> 9.5401969e+08 | H11: =SUM(H4:H10) -> 1.1597055e+09 | I11: =SUM(I4:I10) -> 1.4196045e+09 | J11: =SUM(J4:J10) -> 1.7781836e+09 | K11: =SUM(K4:K10) -> 2.2278684e+09 | L11: =SUM(L4:L10) -> 2.7913543e+09 | ... P11: =SUM(P4:P10) -> 6.869047e+09
A13: FINANCING
A14: Debt service (interest + principal) | E14: =-Financing!E12 -> -5.1413145e+08 | F14: =-Financing!F12 -> -5.1413145e+08 | G14: =-Financing!G12 -> -5.1413145e+08 | H14: =-Financing!H12 -> -5.1413145e+08 | I14: =-Financing!I12 -> 0 | J14: =-Financing!J12 -> 0 | K14: =-Financing!K12 -> 0 | L14: =-Financing!L12 -> 0 | ... P14: =-Financing!P12 -> 0
A15: Dividends paid | E15: =IF(1=1,0,-MAX(PL!E21*PAYOUT,0)) -> 0 | F15: =IF(2=1,0,-MAX(PL!F21*PAYOUT,0)) -> -1.8678425e+08 | G15: =IF(3=1,0,-MAX(PL!G21*PAYOUT,0)) -> -3.3046601e+08 | H15: =IF(4=1,0,-MAX(PL!H21*PAYOUT,0)) -> -4.7001839e+08 | I15: =IF(5=1,0,-MAX(PL!I21*PAYOUT,0)) -> -6.4361686e+08 | J15: =IF(6=1,0,-MAX(PL!J21*PAYOUT,0)) -> -8.2355016e+08 | K15: =IF(7=1,0,-MAX(PL!K21*PAYOUT,0)) -> -1.0489076e+09 | L15: =IF(8=1,0,-MAX(PL!L21*PAYOUT,0)) -> -1.3382332e+09 | M15: =IF(9=1,0,-MAX(PL!M21*PAYOUT,0)) -> -1.691403e+09 | N15: =IF(10=1,0,-MAX(PL!N21*PAYOUT,0)) -> -2.1333599e+09 | O15: =IF(11=1,0,-MAX(PL!O21*PAYOUT,0)) -> -2.6863196e+09 | P15: =IF(12=1,0,-MAX(PL!P21*PAYOUT,0)) -> -3.3780526e+09
A16: memo: dividend WHT withheld | E16: =-E15*0.3*DIV_WHT -> 0 | F16: =-F15*0.3*DIV_WHT -> 8405291.4 | G16: =-G15*0.3*DIV_WHT -> 14870970 | H16: =-H15*0.3*DIV_WHT -> 21150827 | I16: =-I15*0.3*DIV_WHT -> 28962759 | J16: =-J15*0.3*DIV_WHT -> 37059757 | K16: =-K15*0.3*DIV_WHT -> 47200841 | L16: =-L15*0.3*DIV_WHT -> 60220493 | ... P16: =-P15*0.3*DIV_WHT -> 1.5201237e+08
A17: NET FINANCING CASH FLOW | E17: =E14+E15 -> -5.1413145e+08 | F17: =F14+F15 -> -7.009157e+08 | G17: =G14+G15 -> -8.4459746e+08 | H17: =H14+H15 -> -9.8414984e+08 | I17: =I14+I15 -> -6.4361686e+08 | J17: =J14+J15 -> -8.2355016e+08 | K17: =K14+K15 -> -1.0489076e+09 | L17: =L14+L15 -> -1.3382332e+09 | ... P17: =P14+P15 -> -3.3780526e+09
A19: NET MOVEMENT IN CASH | E19: =E11+E17 -> 1.8663556e+09 | F19: =F11+F17 -> 27761149 | G19: =G11+G17 -> 1.0942223e+08 | H19: =H11+H17 -> 1.7555569e+08 | I19: =I11+I17 -> 7.7598763e+08 | J19: =J11+J17 -> 9.546334e+08 | K19: =K11+K17 -> 1.1789608e+09 | L19: =L11+L17 -> 1.4531211e+09 | ... P19: =P11+P17 -> 3.4909945e+09
A20: Opening cash | E20: =0 -> 0 | F20: =E21 -> 1.8663556e+09 | G20: =F21 -> 1.8941168e+09 | H20: =G21 -> 2.003539e+09 | I20: =H21 -> 2.1790947e+09 | J20: =I21 -> 2.9550824e+09 | K20: =J21 -> 3.9097157e+09 | L20: =K21 -> 5.0886765e+09 | M20: =L21 -> 6.5417976e+09 | ... P20: =O21 -> 1.339409e+10
A21: CLOSING CASH | E21: =E20+E19 -> 1.8663556e+09 | F21: =F20+F19 -> 1.8941168e+09 | G21: =G20+G19 -> 2.003539e+09 | H21: =H20+H19 -> 2.1790947e+09 | I21: =I20+I19 -> 2.9550824e+09 | J21: =J20+J19 -> 3.9097157e+09 | K21: =K20+K19 -> 5.0886765e+09 | L21: =L20+L19 -> 6.5417976e+09 | ... P21: =P20+P19 -> 1.6885084e+10
A23: CFADS (for DSCR) | E23: =E11 -> 2.3804871e+09 | F23: =F11 -> 7.2867685e+08 | G23: =G11 -> 9.5401969e+08 | H23: =H11 -> 1.1597055e+09 | I23: =I11 -> 1.4196045e+09 | J23: =J11 -> 1.7781836e+09 | K23: =K11 -> 2.2278684e+09 | L23: =L11 -> 2.7913543e+09 | ... P23: =P11 -> 6.869047e+09

Sheet Balancesheet
A1: Balance Sheet
A2: Operating year | E2: O1 | F2: O2 | G2: O3 | H2: O4 | I2: O5 | J2: O6 | K2: O7 | L2: O8 | M2: O9 | N2: O10 | O2: O11 | P2: O12
A3: ASSETS
A4: Investment property (IAS 40), net | E4: =MAX(IP_V-AssetSplit!E52*(IP_V/(IP_V+PPE_V)),0) -> 4.9910209e+09 | F4: =MAX(IP_V-AssetSplit!F52*(IP_V/(IP_V+PPE_V)),0) -> 4.8944813e+09 | G4: =MAX(IP_V-AssetSplit!G52*(IP_V/(IP_V+PPE_V)),0) -> 4.7979417e+09 | H4: =MAX(IP_V-AssetSplit!H52*(IP_V/(IP_V+PPE_V)),0) -> 4.7014022e+09 | I4: =MAX(IP_V-AssetSplit!I52*(IP_V/(IP_V+PPE_V)),0) -> 4.6048626e+09 | J4: =MAX(IP_V-AssetSplit!J52*(IP_V/(IP_V+PPE_V)),0) -> 4.5083231e+09 | K4: =MAX(IP_V-AssetSplit!K52*(IP_V/(IP_V+PPE_V)),0) -> 4.4117835e+09 | L4: =MAX(IP_V-AssetSplit!L52*(IP_V/(IP_V+PPE_V)),0) -> 4.3347236e+09 | ... P4: =MAX(IP_V-AssetSplit!P52*(IP_V/(IP_V+PPE_V)),0) -> 4.0264837e+09
A5: PPE (IAS 16), net | E5: =MAX(PPE_V-AssetSplit!E52*(PPE_V/(IP_V+PPE_V)),0) -> 2.5825478e+08 | F5: =MAX(PPE_V-AssetSplit!F52*(PPE_V/(IP_V+PPE_V)),0) -> 2.5325945e+08 | G5: =MAX(PPE_V-AssetSplit!G52*(PPE_V/(IP_V+PPE_V)),0) -> 2.4826411e+08 | H5: =MAX(PPE_V-AssetSplit!H52*(PPE_V/(IP_V+PPE_V)),0) -> 2.4326878e+08 | I5: =MAX(PPE_V-AssetSplit!I52*(PPE_V/(IP_V+PPE_V)),0) -> 2.3827345e+08 | J5: =MAX(PPE_V-AssetSplit!J52*(PPE_V/(IP_V+PPE_V)),0) -> 2.3327812e+08 | K5: =MAX(PPE_V-AssetSplit!K52*(PPE_V/(IP_V+PPE_V)),0) -> 2.2828279e+08 | L5: =MAX(PPE_V-AssetSplit!L52*(PPE_V/(IP_V+PPE_V)),0) -> 2.2429541e+08 | ... P5: =MAX(PPE_V-AssetSplit!P52*(PPE_V/(IP_V+PPE_V)),0) -> 2.0834588e+08
A6: Inventory (IAS 2) | E6: =IF(1=1,0,0) -> 0 | F6: =IF(2=1,0,0) -> 0 | G6: =IF(3=1,0,0) -> 0 | H6: =IF(4=1,0,0) -> 0 | I6: =IF(5=1,0,0) -> 0 | J6: =IF(6=1,0,0) -> 0 | K6: =IF(7=1,0,0) -> 0 | L6: =IF(8=1,0,0) -> 0 | M6: =IF(9=1,0,0) -> 0 | N6: =IF(10=1,0,0) -> 0 | O6: =IF(11=1,0,0) -> 0 | P6: =IF(12=1,0,0) -> 0
A7: Cash | E7: =CashFlow!E21 -> 1.8663556e+09 | F7: =CashFlow!F21 -> 1.8941168e+09 | G7: =CashFlow!G21 -> 2.003539e+09 | H7: =CashFlow!H21 -> 2.1790947e+09 | I7: =CashFlow!I21 -> 2.9550824e+09 | J7: =CashFlow!J21 -> 3.9097157e+09 | K7: =CashFlow!K21 -> 5.0886765e+09 | L7: =CashFlow!L21 -> 6.5417976e+09 | ... P7: =CashFlow!P21 -> 1.6885084e+10
A8: TOTAL ASSETS | E8: =SUM(E4:E7) -> 7.1156313e+09 | F8: =SUM(F4:F7) -> 7.0418575e+09 | G8: =SUM(G4:G7) -> 7.0497449e+09 | H8: =SUM(H4:H7) -> 7.1237657e+09 | I8: =SUM(I4:I7) -> 7.7982185e+09 | J8: =SUM(J4:J7) -> 8.651317e+09 | K8: =SUM(K4:K7) -> 9.7287429e+09 | L8: =SUM(L4:L7) -> 1.1100817e+10 | ... P8: =SUM(P4:P7) -> 2.1119914e+10
A10: LIABILITIES
A11: Debt | E11: =Financing!E11 -> 1.0830084e+09 | F11: =Financing!F11 -> 7.8547861e+08 | G11: =Financing!G11 -> 4.2844288e+08 | H11: =Financing!H11 -> 0 | I11: =Financing!I11 -> 0 | J11: =Financing!J11 -> 0 | K11: =Financing!K11 -> 0 | L11: =Financing!L11 -> 0 | ... P11: =Financing!P11 -> 0
A12: Deferred revenue (key money) | E12: =MAX(RETAIL_TOT*(1-SOLD_PCT)*KEY_MONEY*(1-1/10),0) -> 0 | F12: =MAX(RETAIL_TOT*(1-SOLD_PCT)*KEY_MONEY*(1-2/10),0) -> 0 | G12: =MAX(RETAIL_TOT*(1-SOLD_PCT)*KEY_MONEY*(1-3/10),0) -> 0 | H12: =MAX(RETAIL_TOT*(1-SOLD_PCT)*KEY_MONEY*(1-4/10),0) -> 0 | I12: =MAX(RETAIL_TOT*(1-SOLD_PCT)*KEY_MONEY*(1-5/10),0) -> 0 | J12: =MAX(RETAIL_TOT*(1-SOLD_PCT)*KEY_MONEY*(1-6/10),0) -> 0 | K12: =MAX(RETAIL_TOT*(1-SOLD_PCT)*KEY_MONEY*(1-7/10),0) -> 0 | L12: =MAX(RETAIL_TOT*(1-SOLD_PCT)*KEY_MONEY*(1-8/10),0) -> 0 | M12: =MAX(RETAIL_TOT*(1-SOLD_PCT)*KEY_MONEY*(1-9/10),0) -> 0 | N12: =MAX(RETAIL_TOT*(1-SOLD_PCT)*KEY_MONEY*(1-10/10),0) -> 0 | O12: =MAX(RETAIL_TOT*(1-SOLD_PCT)*KEY_MONEY*(1-11/10),0) -> 0 | P12: =MAX(RETAIL_TOT*(1-SOLD_PCT)*KEY_MONEY*(1-12/10),0) -> 0
A13: Deferred tax liability | E13: =Tax!E29 -> 4.6959986e+08 | F13: =Tax!F29 -> 5.0657165e+08 | G13: =Tax!G29 -> 5.4102872e+08 | H13: =Tax!H29 -> 5.7347403e+08 | I13: =Tax!I29 -> 6.0430991e+08 | J13: =Tax!J29 -> 6.3385827e+08 | K13: =Tax!K29 -> 6.6237659e+08 | L13: =Tax!L29 -> 6.9621715e+08 | ... P13: =Tax!P29 -> 8.2617909e+08
A14: TOTAL LIABILITIES | E14: =SUM(E11:E13) -> 1.5526082e+09 | F14: =SUM(F11:F13) -> 1.2920503e+09 | G14: =SUM(G11:G13) -> 9.694716e+08 | H14: =SUM(H11:H13) -> 5.7347403e+08 | I14: =SUM(I11:I13) -> 6.0430991e+08 | J14: =SUM(J11:J13) -> 6.3385827e+08 | K14: =SUM(K11:K13) -> 6.6237659e+08 | L14: =SUM(L11:L13) -> 6.9621715e+08 | ... P14: =SUM(P11:P13) -> 8.2617909e+08
A16: EQUITY
A17: TDOMA equity (cash contributed) | E17: =EQ_TDOMA -> 3.9928496e+09 | F17: =EQ_TDOMA -> 3.9928496e+09 | G17: =EQ_TDOMA -> 3.9928496e+09 | H17: =EQ_TDOMA -> 3.9928496e+09 | I17: =EQ_TDOMA -> 3.9928496e+09 | J17: =EQ_TDOMA -> 3.9928496e+09 | K17: =EQ_TDOMA -> 3.9928496e+09 | L17: =EQ_TDOMA -> 3.9928496e+09 | ... P17: =EQ_TDOMA -> 3.9928496e+09
A18: NCI - City land contributed in-kind | E18: =LAND_V+PL!E21*0.3+CashFlow!E15*0.3 -> 1.662052e+09 | F18: =E18+PL!F21*0.3+CashFlow!F15*0.3 -> 1.7180873e+09 | G18: =F18+PL!G21*0.3+CashFlow!G15*0.3 -> 1.8172271e+09 | H18: =G18+PL!H21*0.3+CashFlow!H15*0.3 -> 1.9582326e+09 | I18: =H18+PL!I21*0.3+CashFlow!I15*0.3 -> 2.1513177e+09 | J18: =I18+PL!J21*0.3+CashFlow!J15*0.3 -> 2.3983827e+09 | K18: =J18+PL!K21*0.3+CashFlow!K15*0.3 -> 2.713055e+09 | L18: =K18+PL!L21*0.3+CashFlow!L15*0.3 -> 3.114525e+09 | M18: =L18+PL!M21*0.3+CashFlow!M15*0.3 -> 3.6219459e+09 | ... P18: =O18+PL!P21*0.3+CashFlow!P15*0.3 -> 6.0812655e+09
A19: Legal reserve (Commercial Code Art. 434) | E19: =MIN(LEGAL_RESERVE_PCT*MAX(PL!E21*0.7,0),LEGAL_RESERVE_PCT*EQ_TDOMA) -> 0 | F19: =E19+MIN(LEGAL_RESERVE_PCT*MAX(PL!F21*0.7,0),MAX(LEGAL_RESERVE_PCT*EQ_TDOMA-E19,0)) -> 0 | G19: =F19+MIN(LEGAL_RESERVE_PCT*MAX(PL!G21*0.7,0),MAX(LEGAL_RESERVE_PCT*EQ_TDOMA-F19,0)) -> 0 | H19: =G19+MIN(LEGAL_RESERVE_PCT*MAX(PL!H21*0.7,0),MAX(LEGAL_RESERVE_PCT*EQ_TDOMA-G19,0)) -> 0 | I19: =H19+MIN(LEGAL_RESERVE_PCT*MAX(PL!I21*0.7,0),MAX(LEGAL_RESERVE_PCT*EQ_TDOMA-H19,0)) -> 0 | J19: =I19+MIN(LEGAL_RESERVE_PCT*MAX(PL!J21*0.7,0),MAX(LEGAL_RESERVE_PCT*EQ_TDOMA-I19,0)) -> 0 | K19: =J19+MIN(LEGAL_RESERVE_PCT*MAX(PL!K21*0.7,0),MAX(LEGAL_RESERVE_PCT*EQ_TDOMA-J19,0)) -> 0 | L19: =K19+MIN(LEGAL_RESERVE_PCT*MAX(PL!L21*0.7,0),MAX(LEGAL_RESERVE_PCT*EQ_TDOMA-K19,0)) -> 0 | M19: =L19+MIN(LEGAL_RESERVE_PCT*MAX(PL!M21*0.7,0),MAX(LEGAL_RESERVE_PCT*EQ_TDOMA-L19,0)) -> 0 | ... P19: =O19+MIN(LEGAL_RESERVE_PCT*MAX(PL!P21*0.7,0),MAX(LEGAL_RESERVE_PCT*EQ_TDOMA-O19,0)) -> 0
A20: Retained earnings | E20: =-PREOPEN+PL!E21*0.7-E19+CashFlow!E15*0.7 -> -91878589 | F20: =E20+PL!F21*0.7-(F19-E19)+CashFlow!F15*0.7 -> 38870388 | G20: =F20+PL!G21*0.7-(G19-F19)+CashFlow!G15*0.7 -> 2.7019659e+08 | H20: =G20+PL!H21*0.7-(H19-G19)+CashFlow!H15*0.7 -> 5.9920946e+08 | I20: =H20+PL!I21*0.7-(I19-H19)+CashFlow!I15*0.7 -> 1.0497413e+09 | J20: =I20+PL!J21*0.7-(J19-I19)+CashFlow!J15*0.7 -> 1.6262264e+09 | K20: =J20+PL!K21*0.7-(K19-J19)+CashFlow!K15*0.7 -> 2.3604617e+09 | L20: =K20+PL!L21*0.7-(L19-K19)+CashFlow!L15*0.7 -> 3.2972249e+09 | M20: =L20+PL!M21*0.7-(M19-L19)+CashFlow!M15*0.7 -> 4.481207e+09 | ... P20: =O20+PL!P21*0.7-(P19-O19)+CashFlow!P15*0.7 -> 1.0219619e+10
A21: TOTAL EQUITY | E21: =SUM(E17:E20) -> 5.563023e+09 | F21: =SUM(F17:F20) -> 5.7498073e+09 | G21: =SUM(G17:G20) -> 6.0802733e+09 | H21: =SUM(H17:H20) -> 6.5502917e+09 | I21: =SUM(I17:I20) -> 7.1939085e+09 | J21: =SUM(J17:J20) -> 8.0174587e+09 | K21: =SUM(K17:K20) -> 9.0663663e+09 | L21: =SUM(L17:L20) -> 1.0404599e+10 | ... P21: =SUM(P17:P20) -> 2.0293735e+10
A23: TOTAL EQUITY & LIABILITIES | E23: =E14+E21 -> 7.1156313e+09 | F23: =F14+F21 -> 7.0418575e+09 | G23: =G14+G21 -> 7.0497449e+09 | H23: =H14+H21 -> 7.1237657e+09 | I23: =I14+I21 -> 7.7982185e+09 | J23: =J14+J21 -> 8.651317e+09 | K23: =K14+K21 -> 9.7287429e+09 | L23: =L14+L21 -> 1.1100817e+10 | ... P23: =P14+P21 -> 2.1119914e+10
A25: CHECK: assets - (equity + liabilities) | E25: =E8-E23 -> 0 | F25: =F8-F23 -> 0 | G25: =G8-G23 -> 0 | H25: =H8-H23 -> 0 | I25: =I8-I23 -> 0 | J25: =J8-J23 -> 0 | K25: =K8-K23 -> 0 | L25: =L8-L23 -> 0 | ... P25: =P8-P23 -> 0

Sheet VAT
A1: VAT Schedule
A3: Operating year | E3: O1 | F3: O2 | G3: O3 | H3: O4 | I3: O5 | J3: O6 | K3: O7 | L3: O8 | M3: O9 | N3: O10 | O3: O11 | P3: O12
A5: OUTPUT VAT — on revenue (extracted from GROSS quoted rates; IFRS 15.47)
A6: Output VAT collected | E6: =Revenue!E25 -> 3.5057512e+08 | F6: =Revenue!F25 -> 1.7844928e+08 | G6: =Revenue!G25 -> 2.4155346e+08 | H6: =Revenue!H25 -> 3.0051016e+08 | I6: =Revenue!I25 -> 3.7410582e+08 | J6: =Revenue!J25 -> 4.6599316e+08 | K6: =Revenue!K25 -> 5.807376e+08 | L6: =Revenue!L25 -> 7.2404538e+08 | ... P6: =Revenue!P25 -> 1.7550764e+09
A7: INPUT VAT — recoverable
A8: Input VAT recovered (opex: property + cloud) | E8: =Opex!E13 -> 26239968 | F8: =Opex!F13 -> 27551966 | G8: =Opex!G13 -> 28929565 | H8: =Opex!H13 -> 30376043 | I8: =Opex!I13 -> 31894845 | J8: =Opex!J13 -> 33489587 | K8: =Opex!K13 -> 35164067 | L8: =Opex!L13 -> 36922270 | ... P8: =Opex!P13 -> 44879250
A9: Input VAT recovered (capex, O1 only — credited to opening equity, not this cash line) | E9: =CashFlow!E10 -> 6.2931121e+08 | F9: =CashFlow!F10 -> 0 | G9: =CashFlow!G10 -> 0 | H9: =CashFlow!H10 -> 0 | I9: =CashFlow!I10 -> 0 | J9: =CashFlow!J10 -> 0 | K9: =CashFlow!K10 -> 0 | L9: =CashFlow!L10 -> 0 | ... P9: =CashFlow!P10 -> 0
A10: TOTAL INPUT VAT RECOVERED (operating only, per note in row 9) | E10: =E8 -> 26239968 | F10: =F8 -> 27551966 | G10: =G8 -> 28929565 | H10: =H8 -> 30376043 | I10: =I8 -> 31894845 | J10: =J8 -> 33489587 | K10: =K8 -> 35164067 | L10: =L8 -> 36922270 | ... P10: =P8 -> 44879250
A11: NET POSITION
A12: NET VAT (+ = due to tax authority, − = refund due) | E12: =E6-E10 -> 3.2433515e+08 | F12: =F6-F10 -> 1.5089732e+08 | G12: =G6-G10 -> 2.1262389e+08 | H12: =H6-H10 -> 2.7013412e+08 | I12: =I6-I10 -> 3.4221097e+08 | J12: =J6-J10 -> 4.3250357e+08 | K12: =K6-K10 -> 5.4557353e+08 | L12: =L6-L10 -> 6.8712311e+08 | ... P12: =P6-P10 -> 1.7101972e+09
A13: Memo — total incl. one-off capex VAT refund (informational only)
A14: NET VAT incl. capex refund (memo) | E14: =E6-E8-E9 -> -3.0497606e+08 | F14: =F6-F8-F9 -> 1.5089732e+08 | G14: =G6-G8-G9 -> 2.1262389e+08 | H14: =H6-H8-H9 -> 2.7013412e+08 | I14: =I6-I8-I9 -> 3.4221097e+08 | J14: =J6-J8-J9 -> 4.3250357e+08 | K14: =K6-K8-K9 -> 5.4557353e+08 | L14: =L6-L8-L9 -> 6.8712311e+08 | ... P14: =P6-P8-P9 -> 1.7101972e+09

Sheet Checks
A1: Integrity Checks
A2: Check | B2: Value | C2: Status | D2: Note | E2: Type
A3: Balance sheet balances, every year | B3: =SUMPRODUCT(ABS(Balancesheet!E25:P25)) -> 0 | C3: =IF(B3<=1,"PASS","FAIL") -> PASS | D3: Sum of |assets - E&L| across all 12 years | E3: Independent
A4: Cash flow closing cash = balance-sheet cash | B4: =SUMPRODUCT(ABS(CashFlow!E21:P21-Balancesheet!E7:P7)) -> 0 | C4: =IF(B4<=1,"PASS","FAIL") -> PASS | D4: IAS 7 ties to BS | E4: Independent
A5: Sources = Uses | B5: =ABS(Capex!$B$29) -> 0 | C5: =IF(B5<=1,"PASS","FAIL") -> PASS | D5: Capex sheet funding check | E5: Independent
A6: Capex splits to IAS 2 / IAS 40 / IAS 16 without leakage (net of recoverable VAT) | B6: =ABS(AssetSplit!$B$22) -> 0 | C6: =IF(B6<=1,"PASS","FAIL") -> PASS | D6: Inventory + PPE + IP = capex − recoverable VAT | E6: Structural — IP is a residual (capex less the other two) by definition; cannot fail without a coding error
A7: Debt fully repaid within tenor | B7: =ABS(Financing!K11) -> 0 | C7: =IF(B7<=1,"PASS","FAIL") -> PASS | D7: Closing balance at end of amortisation | E7: Independent
A8: Sum of principal = debt drawn | B8: =ABS(SUM(Financing!E10:P10)-Financing!$B$3) -> 0 | C8: =IF(B8<=1,"PASS","FAIL") -> PASS | D8: No leakage in the loan schedule | E8: Structural — the annuity is solved to amortise exactly this amount
A9: Inventory fully released to cost of sales | B9: =ABS(SUM(PL!E10:P10)+INVENTORY_V) -> 0 | C9: =IF(B9<=1,"PASS","FAIL") -> PASS | D9: All units sold at handover | E9: Structural — cost of sales is defined as the full inventory balance at O1
A10: Key-money deferred revenue released by O10 | B10: =ABS(Balancesheet!N12) -> 0 | C10: =IF(B10<=1,"PASS","FAIL") -> PASS | D10: 10-yr lease premium fully recognised | E10: Structural — the release schedule divides by exactly 10 years
A11: Land NOT depreciated (IAS 16.58) | B11: =ABS(AssetSplit!$B$37-(AssetSplit!$B$35/LIFE_B+AssetSplit!$B$33/LIFE_S+AssetSplit!$B$34/LIFE_F)) -> 0 | C11: =IF(B11<=1,"PASS","FAIL") -> PASS | D11: Depreciation excludes the land line | E11: Independent
A12: Revenue areas reconcile to net GLA + warehouse | B12: =ABS(Revenue!$B$14+RETAIL_TOT*SOLD_PCT+ONE_STOP+HQ_A+CIRCULATION_A+HOTEL_GLA_A+EVENTS_GLA_A-NET_GLA-WAREHOUSE_M2) -> 0 | C12: =IF(B12<=1,"PASS","FAIL") -> PASS | D12: Lettable (incl. warehouse) + sold + hotel + events + non-earning = 21,004 + 6,000 | E12: Independent
A13: DSCR >= covenant every period | B13: =MIN(Financing!E16:K16) -> 1.4172968 | C13: =IF(B13>=DSCR_COV,"PASS","FAIL") -> PASS | D13: EXPECTED FAIL - a genuine finding, not a defect. See Dashboard. | E13: Independent
A14: Cash never negative | B14: =MIN(CashFlow!E21:P21) -> 1.8663556e+09 | C14: =IF(B14>=0,"PASS","FAIL") -> PASS | E14: Independent
A15: IAS 36: carrying value <= value in use, every year (no impairment) | B15: =MIN(Returns!E36:P36) -> 5.0158934e+09 | C15: =IF(B15>=0,"PASS","FAIL") -> PASS | D15: Value in use exceeds carrying amount every year. | E15: Independent
A17: CHECKS PASSING | B17: =COUNTIF(C3:C15,"PASS")&" / "&COUNTA(C3:C15) -> 13 / 13 | D17: =" of which "&COUNTIF(E3:E15,"Independent")&" independent, "&(COUNTA(E3:E15)-COUNTIF(E3:E15,"Independent"))&" structural (see Type column)" -> of which 9 independent, 4 structural (see Type column)

Sheet TaxLaw
A1: Tax & Law Register
A2: Item | B2: Value | C2: Statutory source | D2: Effective | E2: Confidence | F2: Note
A3: Corporate income tax | B3: =CIT -> 0.3 | C3: Income Tax Proclamation No. 979/2016 | D3: In force | E3: MED | F3: Headline 30%; applied in Tax sheet
A4: VAT | B4: =VAT_R -> 0.15 | C4: VAT Proclamation No. 1341/2024; Regulation No. 570/2025 | D4: 2024/2025 | E4: MED | F4: See VAT sheet — output/input
A5: Tax depreciation - building pool | B5: =TAX_DEP -> 0.05 | C5: Income Tax Proclamation No. 979/2016 | D5: In force | E5: MED | F5: 5% SL; drives deferred tax
A6: Tax depreciation - plant & machinery pool | B6: =TAX_DEP_PLANT -> 0.2 | C6: Income Tax Proclamation No. 979/2016 — pool/diminishing-value method | D6: 21 Jul 2026 | E6: LOW | F6: Specialist systems + FF&E; rate to confirm with tax counsel
A7: Dividend withholding | B7: =DIV_WHT -> 0.15 | C7: Income Tax Proclamation No. 979/2016 | D7: In force | E7: HIGH | F7: 15% standard; exempt for a resident corporate holder of >=12.5% with control (TDOMA's 70%)
A8: Undistributed-profits tax | B8: =UNDIST_TAX_RATE -> 0 | C8: Proclamation No. 1395/2025 | D8: 21 Jul 2026 | E8: HIGH | F8: 15% on PAT retained (not distributed) each year
A9: Property tax | B9: =PROP_TAX -> 0.01 | C9: Property Tax Proclamation No. 1365/2025 | D9: 2025 | E9: LOW | F9: Assessed-value base to be confirmed with assessor
A10: Financial reporting framework | B10: IFRS | C10: Financial Reporting Proclamation No. 847/2014 (AABE) | D10: In force | E10: HIGH | F10: Full IFRS mandated
A11: Capital markets | B11: n/a | C11: Capital Market Proclamation No. 1248/2021; ECMA Directive 1030/2024 | D11: 2021/2024 | E11: MED | F11: Model must support a prospectus
A12: PPP framework | B12: n/a | C12: PPP Proclamation No. 1076/2018 as amended by 1283/2023 | D12: 2018/2023 | E12: MED | F12: 70/30 structure; land in-kind
A13: Related-party transactions | B13: n/a | C13: Commercial Code (Trade Registration and Business Licensing) Art. 395 | D13: 21 Jul 2026 | E13: LOW | F13: OUTSTANDING: the 1,684,800,000 ETB retail sale to shareholder-merchants has NO recorded board/shareholder approval, auditor's report, or MoTI filing on file. Under Art. 395(6) the sale remains legally VOIDABLE until obtained -- this is a legal/governance action, not something a model can fix; flagged here so it is not lost.
A14: Legal reserve | B14: =LEGAL_RESERVE_PCT -> 0 | C14: Commercial Code Art. 434 | D14: 21 Jul 2026 | E14: HIGH | F14: 5% of net profit until the reserve reaches 5% of paid-in capital — see ChangesInEquity sheet
A16: IFRS TREATMENTS APPLIED
A17: IFRS 15 | C17: Retail unit sales - POINT IN TIME at handover. Sale is after construction, so no enforceable right to payment for work done.
A18: IAS 2 | C18: Retail units for sale = inventory. Carrying amount -> cost of sales on handover. See AssetSplit.
A19: IAS 40 | C19: Retained let space = investment property, COST model (audit-friendly default).
A20: IFRS 16 (lessor) | C20: Tenant rents; hotel turnover rent = variable lease payment, recognised as earned; key money = lease premium, deferred.
A21: IAS 16 | C21: TDOMA HQ owner-occupied = PPE. 16.17(a) capitalises in-house design; 16.19(b)/(c) FORBID capitalising pre-opening.
A22: IAS 23 | C22: IDC capitalised into the qualifying asset during construction. Arrangement fee is a borrowing cost.
A23: IAS 12 | C23: Deferred tax on the gap between accounting NBV and tax WDV. See Tax sheet.
A24: IAS 16.58 | C24: Land NOT depreciated.

Sheet Returns
A1: DCF & Investment Metrics
A2: Period | D2: C1 | E2: C2 | F2: C3 | G2: O1 | H2: O2 | I2: O3 | J2: O4 | K2: O5 | L2: O6 | M2: O7 | N2: O8 | O2: O9 | P2: O10 | Q2: O11 | R2: O12
A3: S-curve draw (construction) | D3: =SUM(IDC!$B$3:$B$14) -> 0.25925926 | E3: =SUM(IDC!$B$15:$B$26) -> 0.48148148 | F3: =SUM(IDC!$B$27:$B$38) -> 0.25925926
A4: Project cash flow | D4: =-BUILDING*D3 -> -1.3491332e+09 | E4: =-BUILDING*E3 -> -2.5055331e+09 | F4: =-BUILDING*F3-PREOPEN -> -1.4691332e+09 | G4: =PL!E13-PL!E10+PL!E18+PL!E20+CashFlow!E10 -> 2.3804871e+09 | H4: =PL!F13-PL!F10+PL!F18+PL!F20+CashFlow!F10 -> 7.2867685e+08 | I4: =PL!G13-PL!G10+PL!G18+PL!G20+CashFlow!G10 -> 9.5401969e+08 | J4: =PL!H13-PL!H10+PL!H18+PL!H20+CashFlow!H10 -> 1.1597055e+09 | K4: =PL!I13-PL!I10+PL!I18+PL!I20+CashFlow!I10 -> 1.4196045e+09 | L4: =PL!J13-PL!J10+PL!J18+PL!J20+CashFlow!J10 -> 1.7781836e+09 | M4: =PL!K13-PL!K10+PL!K18+PL!K20+CashFlow!K10 -> 2.2278684e+09 | N4: =PL!L13-PL!L10+PL!L18+PL!L20+CashFlow!L10 -> 2.7913543e+09 | ... Q4: =PL!O13-PL!O10+PL!O18+PL!O20+CashFlow!O10 -> 5.4859187e+09 | R4: =PL!P13-PL!P10+PL!P18+PL!P20+$B$9+CashFlow!P10 -> 2.1188323e+10
A5: Equity cash flow (TDOMA: own cash in, 70% share out) | D5: =-EQ_TDOMA*D3 -> -1.0351832e+09 | E5: =-EQ_TDOMA*E3 -> -1.9224831e+09 | F5: =-EQ_TDOMA*F3 -> -1.0351832e+09 | G5: =(G4-Financing!E12)*0.7 -> 1.3064489e+09 | H5: =(H4-Financing!F12)*0.7 -> 1.5018178e+08 | I5: =(I4-Financing!G12)*0.7 -> 3.0792177e+08 | J5: =(J4-Financing!H12)*0.7 -> 4.5190186e+08 | K5: =(K4-Financing!I12)*0.7 -> 9.9372315e+08 | L5: =(L4-Financing!J12)*0.7 -> 1.2447285e+09 | M5: =(M4-Financing!K12)*0.7 -> 1.5595079e+09 | N5: =(N4-Financing!L12)*0.7 -> 1.953948e+09 | ... R5: =(R4-Financing!P12)*0.7 -> 1.4831826e+10
A7: TERMINAL VALUE & METRICS
A8: Stabilised NOI (O3 EBITDA) | B8: =PL!G13 -> 1.2028192e+09
A9: Terminal value @ exit cap | B9: =$B$8*(1+RENT_ESC)/EXIT_CAP -> 1.4319276e+10
A11: Project NPV @ 20% | B11: =D4+NPV(DISC,E4:R4) -> 2.8607793e+09
A12: Project IRR | B12: =IRR(D4:R4) -> 0.28306433
A13: Equity NPV @ 20% | B13: =D5+NPV(COE,E5:R5) -> 1.1195424e+09
A14: Equity IRR | B14: =IRR(D5:R5) -> 0.2419003
A16: Yield on cost (stab. NOI / capex) | B16: =$B$8/CAPEX -> 0.1754967
A17: Equity MoIC | B17: =SUMIF(D5:R5,">0")/-SUMIF(D5:R5,"<0") -> 8.0530332
A18: Gearing at COD (debt / capex) | B18: =DEBT_V/CAPEX -> 0.19419154
A19: Minimum DSCR | B19: =MIN(Financing!E16:K16) -> 1.4172968
A20: Average DSCR | B20: =AVERAGE(Financing!E16:K16) -> 2.5396662
A22: GDV vs COST (is the project viable?)
A23: GDV - retained (stab. NOI @ exit cap) | B23: =$B$9 -> 1.4319276e+10
A24: GDV - sold retail | B24: =RETAIL_TOT*SOLD_PCT*SALE_PRICE -> 1684800000
A25: TOTAL GDV | B25: =B23+B24 -> 1.6004076e+10
A26: TOTAL CAPEX | B26: =CAPEX -> 6.8537994e+09
A27: DEVELOPMENT MARGIN | B27: =B25-B26 -> 9.1502766e+09
A28: PROFIT ON COST | B28: =B27/B26 -> 1.3350663
A30: EFFECTIVE capex per TDOMA net GLA m2 | B30: =CAPEX/(NET_GLA*0.7) -> 466156.07
A32: IAS 36 IMPAIRMENT TEST (audit-confirmed gap: no test previously existed)
A33: Year | E33: O1 | F33: O2 | G33: O3 | H33: O4 | I33: O5 | J33: O6 | K33: O7 | L33: O8 | M33: O9 | N33: O10 | O33: O11 | P33: O12
A34: Carrying amount (IP + PPE, NBV) | E34: =Balancesheet!E4+Balancesheet!E5 -> 5.2492756e+09 | F34: =Balancesheet!F4+Balancesheet!F5 -> 5.1477407e+09 | G34: =Balancesheet!G4+Balancesheet!G5 -> 5.0462059e+09 | H34: =Balancesheet!H4+Balancesheet!H5 -> 4.944671e+09 | I34: =Balancesheet!I4+Balancesheet!I5 -> 4.8431361e+09 | J34: =Balancesheet!J4+Balancesheet!J5 -> 4.7416012e+09 | K34: =Balancesheet!K4+Balancesheet!K5 -> 4.6400663e+09 | L34: =Balancesheet!L4+Balancesheet!L5 -> 4.559019e+09 | ... P34: =Balancesheet!P4+Balancesheet!P5 -> 4.2348295e+09
A35: Value in use (PV of future cash flows + TV, disc. @ hurdle) | E35: =Payback!H4/(1+DISC)^1+Payback!I4/(1+DISC)^2+Payback!J4/(1+DISC)^3+Payback!K4/(1+DISC)^4+Payback!L4/(1+DISC)^5+Payback!M4/(1+DISC)^6+Payback!N4/(1+DISC)^7+Payback!O4/(1+DISC)^8+Payback!P4/(1+DISC)^9+Payback!Q4/(1+DISC)^10+Payback!R4/(1+DISC)^11+$B$9/(1+DISC)^11 -> 1.0265169e+10 | F35: =Payback!I4/(1+DISC)^1+Payback!J4/(1+DISC)^2+Payback!K4/(1+DISC)^3+Payback!L4/(1+DISC)^4+Payback!M4/(1+DISC)^5+Payback!N4/(1+DISC)^6+Payback!O4/(1+DISC)^7+Payback!P4/(1+DISC)^8+Payback!Q4/(1+DISC)^9+Payback!R4/(1+DISC)^10+$B$9/(1+DISC)^10 -> 1.1589526e+10 | G35: =Payback!J4/(1+DISC)^1+Payback!K4/(1+DISC)^2+Payback!L4/(1+DISC)^3+Payback!M4/(1+DISC)^4+Payback!N4/(1+DISC)^5+Payback!O4/(1+DISC)^6+Payback!P4/(1+DISC)^7+Payback!Q4/(1+DISC)^8+Payback!R4/(1+DISC)^9+$B$9/(1+DISC)^9 -> 1.2953412e+10 | H35: =Payback!K4/(1+DISC)^1+Payback!L4/(1+DISC)^2+Payback!M4/(1+DISC)^3+Payback!N4/(1+DISC)^4+Payback!O4/(1+DISC)^5+Payback!P4/(1+DISC)^6+Payback!Q4/(1+DISC)^7+Payback!R4/(1+DISC)^8+$B$9/(1+DISC)^8 -> 1.4384388e+10 | I35: =Payback!L4/(1+DISC)^1+Payback!M4/(1+DISC)^2+Payback!N4/(1+DISC)^3+Payback!O4/(1+DISC)^4+Payback!P4/(1+DISC)^5+Payback!Q4/(1+DISC)^6+Payback!R4/(1+DISC)^7+$B$9/(1+DISC)^7 -> 1.5841661e+10 | J35: =Payback!M4/(1+DISC)^1+Payback!N4/(1+DISC)^2+Payback!O4/(1+DISC)^3+Payback!P4/(1+DISC)^4+Payback!Q4/(1+DISC)^5+Payback!R4/(1+DISC)^6+$B$9/(1+DISC)^6 -> 1.723181e+10 | K35: =Payback!N4/(1+DISC)^1+Payback!O4/(1+DISC)^2+Payback!P4/(1+DISC)^3+Payback!Q4/(1+DISC)^4+Payback!R4/(1+DISC)^5+$B$9/(1+DISC)^5 -> 1.8450304e+10 | L35: =Payback!O4/(1+DISC)^1+Payback!P4/(1+DISC)^2+Payback!Q4/(1+DISC)^3+Payback!R4/(1+DISC)^4+$B$9/(1+DISC)^4 -> 1.934901e+10 | M35: =Payback!P4/(1+DISC)^1+Payback!Q4/(1+DISC)^2+Payback!R4/(1+DISC)^3+$B$9/(1+DISC)^3 -> 1.9721778e+10 | N35: =Payback!Q4/(1+DISC)^1+Payback!R4/(1+DISC)^2+$B$9/(1+DISC)^2 -> 1.9285712e+10 | O35: =Payback!R4/(1+DISC)^1+$B$9/(1+DISC)^1 -> 1.7656936e+10 | P35: =$B$9/(1+DISC)^0 -> 1.4319276e+10
A36: Headroom (VIU - carrying) | E36: =E35-E34 -> 5.0158934e+09 | F36: =F35-F34 -> 6.4417853e+09 | G36: =G35-G34 -> 7.9072057e+09 | H36: =H35-H34 -> 9.4397173e+09 | I36: =I35-I34 -> 1.0998525e+10 | J36: =J35-J34 -> 1.2490209e+10 | K36: =K35-K34 -> 1.3810238e+10 | L36: =L35-L34 -> 1.4789991e+10 | ... P36: =P35-P34 -> 1.0084447e+10
A37: Impairment indicated? | E37: =IF(E36<0,"IMPAIRED","no") -> no | F37: =IF(F36<0,"IMPAIRED","no") -> no | G37: =IF(G36<0,"IMPAIRED","no") -> no | H37: =IF(H36<0,"IMPAIRED","no") -> no | I37: =IF(I36<0,"IMPAIRED","no") -> no | J37: =IF(J36<0,"IMPAIRED","no") -> no | K37: =IF(K36<0,"IMPAIRED","no") -> no | L37: =IF(L36<0,"IMPAIRED","no") -> no | ... P37: =IF(P36<0,"IMPAIRED","no") -> no
A39: Value in use uses the SAME DCF machinery as the project return above, evaluated at each year-end instead of only at t=0. No impairment charge is booked in the P&L/BS even where indicated -- this is the TEST; a genuine write-down would need separate modelling if triggered.

Sheet Payback
A1: Payback Period
A3: Period | D3: C1 | E3: C2 | F3: C3 | G3: O1 | H3: O2 | I3: O3 | J3: O4 | K3: O5 | L3: O6 | M3: O7 | N3: O8 | O3: O9 | P3: O10 | Q3: O11 | R3: O12
A4: Project cash flow (excl. terminal value) | D4: =Returns!D4 -> -1.3491332e+09 | E4: =Returns!E4 -> -2.5055331e+09 | F4: =Returns!F4 -> -1.4691332e+09 | G4: =Returns!G4 -> 2.3804871e+09 | H4: =Returns!H4 -> 7.2867685e+08 | I4: =Returns!I4 -> 9.5401969e+08 | J4: =Returns!J4 -> 1.1597055e+09 | K4: =Returns!K4 -> 1.4196045e+09 | ... Q4: =Returns!Q4 -> 5.4859187e+09 | R4: =Returns!R4-Returns!$B$9 -> 6.869047e+09
A5: Cumulative project cash flow | D5: =D4 -> -1.3491332e+09 | E5: =D5+E4 -> -3.8546663e+09 | F5: =E5+F4 -> -5.3237994e+09 | G5: =F5+G4 -> -2.9433124e+09 | H5: =G5+H4 -> -2.2146355e+09 | I5: =H5+I4 -> -1.2606158e+09 | J5: =I5+J4 -> -1.0091028e+08 | K5: =J5+K4 -> 1.3186942e+09 | L5: =K5+L4 -> 3.0968778e+09 | ... R5: =Q5+R4 -> 2.8348522e+10
A6: Discounted project CF @ DISC | D6: =D4/(1+DISC)^0 -> -1.3491332e+09 | E6: =E4/(1+DISC)^1 -> -2.0879442e+09 | F6: =F4/(1+DISC)^2 -> -1.0202314e+09 | G6: =G4/(1+DISC)^3 -> 1.3775967e+09 | H6: =H4/(1+DISC)^4 -> 3.5140666e+08 | I6: =I4/(1+DISC)^5 -> 3.8339912e+08 | J6: =J4/(1+DISC)^6 -> 3.8838304e+08 | K6: =K4/(1+DISC)^7 -> 3.9618556e+08 | L6: =L4/(1+DISC)^8 -> 4.1354866e+08 | M6: =M4/(1+DISC)^9 -> 4.3177582e+08 | N6: =N4/(1+DISC)^10 -> 4.508193e+08 | O6: =O4/(1+DISC)^11 -> 4.7065886e+08 | P6: =P4/(1+DISC)^12 -> 4.9129338e+08 | Q6: =Q4/(1+DISC)^13 -> 5.1273524e+08 | R6: =R4/(1+DISC)^14 -> 5.3500648e+08
A7: Cumulative discounted project CF | D7: =D6 -> -1.3491332e+09 | E7: =D7+E6 -> -3.4370774e+09 | F7: =E7+F6 -> -4.4573088e+09 | G7: =F7+G6 -> -3.0797121e+09 | H7: =G7+H6 -> -2.7283054e+09 | I7: =H7+I6 -> -2.3449063e+09 | J7: =I7+J6 -> -1.9565233e+09 | K7: =J7+K6 -> -1.5603377e+09 | L7: =K7+L6 -> -1.1467891e+09 | ... R7: =Q7+R6 -> 1.7455e+09
A9: SIMPLE PAYBACK — PROJECT BASIS
A10: Crossing period (index, 1 = C1) | B10: =IFERROR(SUMPRODUCT((D5:R5<0)*1)+1,"never") -> 8
A11: Cumulative CF at prior period | B11: =IFERROR(IF((SUMPRODUCT((D5:R5<0)*1)+1)=1,0,INDEX(D5:R5,(SUMPRODUCT((D5:R5<0)*1)+1)-1)),"") -> -1.0091028e+08
A12: Cash flow at crossing period | B12: =IFERROR(INDEX(D4:R4,SUMPRODUCT((D5:R5<0)*1)+1),"") -> 1.4196045e+09
A13: Fractional recovery in crossing period | B13: =IFERROR(-B11/B12,"") -> 0.071083373
A14: PAYBACK PERIOD (years) | B14: =IFERROR(MAX(B10-1,0)+B13,"beyond horizon") -> 7.0710834
A16: DISCOUNTED PAYBACK — PROJECT BASIS @ DISC
A17: Crossing period (index, 1 = C1) | B17: =IFERROR(SUMPRODUCT((D7:R7<0)*1)+1,"never") -> 12
A18: Cumulative CF at prior period | B18: =IFERROR(IF((SUMPRODUCT((D7:R7<0)*1)+1)=1,0,INDEX(D7:R7,(SUMPRODUCT((D7:R7<0)*1)+1)-1)),"") -> -2.6419394e+08
A19: Cash flow at crossing period | B19: =IFERROR(INDEX(D6:R6,SUMPRODUCT((D7:R7<0)*1)+1),"") -> 4.7065886e+08
A20: Fractional recovery in crossing period | B20: =IFERROR(-B18/B19,"") -> 0.56132788
A21: PAYBACK PERIOD (years) | B21: =IFERROR(MAX(B17-1,0)+B20,"beyond horizon") -> 11.561328
A23: EQUITY BASIS
A24: Equity cash flow (excl. terminal value share) | D24: =Returns!D5 -> -1.0351832e+09 | E24: =Returns!E5 -> -1.9224831e+09 | F24: =Returns!F5 -> -1.0351832e+09 | G24: =Returns!G5 -> 1.3064489e+09 | H24: =Returns!H5 -> 1.5018178e+08 | I24: =Returns!I5 -> 3.0792177e+08 | J24: =Returns!J5 -> 4.5190186e+08 | K24: =Returns!K5 -> 9.9372315e+08 | ... Q24: =Returns!Q5 -> 3.8401431e+09 | R24: =Returns!R5-Returns!$B$9*0.7 -> 4.8083329e+09
A25: Cumulative equity cash flow | D25: =D24 -> -1.0351832e+09 | E25: =D25+E24 -> -2.9576664e+09 | F25: =E25+F24 -> -3.9928496e+09 | G25: =F25+G24 -> -2.6864006e+09 | H25: =G25+H24 -> -2.5362189e+09 | I25: =H25+I24 -> -2.2282971e+09 | J25: =I25+J24 -> -1.7763952e+09 | K25: =J25+K24 -> -7.8267208e+08 | L25: =K25+L24 -> 4.6205641e+08 | ... R25: =Q25+R24 -> 1.8138207e+10
A26: Discounted equity CF @ COE | D26: =D24/(1+COE)^0 -> -1.0351832e+09 | E26: =E24/(1+COE)^1 -> -1.6020693e+09 | F26: =F24/(1+COE)^2 -> -7.1887724e+08 | G26: =G24/(1+COE)^3 -> 7.5604685e+08 | H26: =H24/(1+COE)^4 -> 72425628 | I26: =I24/(1+COE)^5 -> 1.2374685e+08 | J26: =J24/(1+COE)^6 -> 1.5134102e+08 | K26: =K24/(1+COE)^7 -> 2.7732989e+08 | L26: =L24/(1+COE)^8 -> 2.8948406e+08 | M26: =M24/(1+COE)^9 -> 3.0224307e+08 | N26: =N24/(1+COE)^10 -> 3.1557351e+08 | O26: =O24/(1+COE)^11 -> 3.294612e+08 | P26: =P24/(1+COE)^12 -> 3.4390537e+08 | Q26: =Q24/(1+COE)^13 -> 3.5891467e+08 | R26: =R24/(1+COE)^14 -> 3.7450454e+08
A27: Cumulative discounted equity CF | D27: =D26 -> -1.0351832e+09 | E27: =D27+E26 -> -2.6372525e+09 | F27: =E27+F26 -> -3.3561297e+09 | G27: =F27+G26 -> -2.6000829e+09 | H27: =G27+H26 -> -2.5276573e+09 | I27: =H27+I26 -> -2.4039104e+09 | J27: =I27+J26 -> -2.2525694e+09 | K27: =J27+K26 -> -1.9752395e+09 | L27: =K27+L26 -> -1.6857554e+09 | ... R27: =Q27+R26 -> 3.3884691e+08
A29: SIMPLE PAYBACK — EQUITY BASIS
A30: Crossing period (index, 1 = C1) | B30: =IFERROR(SUMPRODUCT((D25:R25<0)*1)+1,"never") -> 9
A31: Cumulative CF at prior period | B31: =IFERROR(IF((SUMPRODUCT((D25:R25<0)*1)+1)=1,0,INDEX(D25:R25,(SUMPRODUCT((D25:R25<0)*1)+1)-1)),"") -> -7.8267208e+08
A32: Cash flow at crossing period | B32: =IFERROR(INDEX(D24:R24,SUMPRODUCT((D25:R25<0)*1)+1),"") -> 1.2447285e+09
A33: Fractional recovery in crossing period | B33: =IFERROR(-B31/B32,"") -> 0.6287894
A34: PAYBACK PERIOD (years) | B34: =IFERROR(MAX(B30-1,0)+B33,"beyond horizon") -> 8.6287894
A36: DISCOUNTED PAYBACK — EQUITY BASIS @ COE
A37: Crossing period (index, 1 = C1) | B37: =IFERROR(SUMPRODUCT((D27:R27<0)*1)+1,"never") -> 15
A38: Cumulative CF at prior period | B38: =IFERROR(IF((SUMPRODUCT((D27:R27<0)*1)+1)=1,0,INDEX(D27:R27,(SUMPRODUCT((D27:R27<0)*1)+1)-1)),"") -> -35657624
A39: Cash flow at crossing period | B39: =IFERROR(INDEX(D26:R26,SUMPRODUCT((D27:R27<0)*1)+1),"") -> 3.7450454e+08
A40: Fractional recovery in crossing period | B40: =IFERROR(-B38/B39,"") -> 0.095212795
A41: PAYBACK PERIOD (years) | B41: =IFERROR(MAX(B37-1,0)+B40,"beyond horizon") -> 14.095213

Sheet Breakeven
A1: Break-even Analysis
A2: A. OCCUPANCY (base blended multiplier 1.00x, physical ceiling ~1.05x)
A3: Target | B3: Blended occ needed | C3: Achievable?
A4: Development margin = 0 | B4: 0.0866 | C4: Yes - very deep cushion below base
A5: DSCR 1.00x (cash-adequate) | B5: 0.4561 | C5: Yes - well below base
A6: DSCR 1.30x (covenant) | B6: 0.8471 | C6: Yes - but only 15% below base; the tightest cash test
A7: Project IRR 20% | B7: 0.3295 | C7: Yes - well below base
A8: Equity IRR 20% | B8: 0.6251 | C8: Yes - comfortably below base
A9: Memo: occupancy needed for Equity IRR 24% = 0.981x (base is 1.00x, so the 24% equity hurdle is cleared at base with only ~2% of occupancy headroom).
A10: B. RENT (uniform multiplier; base blended ~4,390 ETB/m2/mo)
A11: Target | B11: Rent multiplier | C11: Blended rent
A12: Development margin = 0 | B12: 0.0866 | C12: 376
A13: DSCR 1.00x | B13: 0.4561 | C13: 1978
A14: DSCR 1.30x (covenant) | B14: 0.8471 | C14: 3673
A15: Project IRR 20% | B15: 0.3295 | C15: 1429
A16: Equity IRR 24% | B16: 0.981 | C16: 4254
A17: RECOMPUTED. IMPORTANT FINDING: in this model a uniform RENT multiplier and the OCCUPANCY multiplier are the SAME lever mathematically -- OCC_MULT appears only in Revenue rows 7-13 and in STAB_RENT (B15), exactly where a rent multiplier acts, and NEITHER touches hotel turnover rent or other income. Tables A and B must therefore give identical break-even multipliers, and now do. The ORIGINAL sheet reported different figures for the two (margin=0 at 0.10x occupancy but "never" on rent), which was internally inconsistent.
A19: C. RETAIL SALE PRICE (base 540,000 ETB/m2)
A20: Target | B20: Sale price ETB/m2 | C20: vs base
A21: Development margin = 0 | B21: n/r | C21: Unreachable - margin stays positive even at a zero sale price
A22: Project IRR 20% | B22: n/r | C22: Unreachable - IRR is 26.4% even at a zero sale price
A23: Equity IRR 20% | B23: n/r | C23: Unreachable - equity IRR is 22.6% even at a zero sale price
A24: RECOMPUTED. The sale price is NOT a viability lever: margin, project IRR and equity IRR 20% all remain satisfied even if the retail units were given away free. Memo: the price needed to hold Equity IRR at 24% is 472,638 ETB/m2 -- i.e. the base 540,000 could fall 12.5% and still clear the 24% equity hurdle. (The original sheet claimed the price had to rise 23% ABOVE base to clear 24%; that is now reversed by the corrected depreciation and VAT fixes.)
A26: D. SALE-% OF RETAIL (base 75% sold) - a WEAK lever, now barely a lever at all
A27: Target | B27: Sale-% needed | C27: Achievable?
A28: Development margin = 0 | B28: n/r | C28: No - unreachable at ANY %
A29: Project IRR 20% | B29: n/r | C29: No - unreachable at ANY %
A30: DSCR 1.30x (covenant) | B30: n/r | C30: No - unreachable at ANY %
A31: RECOMPUTED. Full 0->100% sale swing moves margin only ~1.17bn (10.02bn at 0% sold to 8.86bn at 100%) - selling actually SHRINKS margin, since retained space earns more than the sale crystallises. It also weakens DSCR (1.63x at 0% sold vs 1.35x at 100%). Not a lever worth pulling; if anything, selling less improves both margin and covenant headroom.
A33: E. MARKET & FINANCING
A34: Condition | B34: Break-even | C34: Note
A35: Exit cap for margin = 0 | B35: 0.3112 | C35: base 10.5%; above this, underwater on GDV
A36: Exit cap for IRR 20% | B36: n/r | C36: not reachable - IRR stays above 27.8% across 5%-99%
A37: Debt rate that would BREACH DSCR 1.30x | B37: 0.2527 | C37: base 20% - about 5pts of headroom before the covenant bites
A38: CAUTION: EXIT_CAP is used TWICE in this model - as the terminal cap rate AND as the capitalisation rate in the property-tax proxy (Opex row 12). The two effects partly offset, so these exit-cap break-evens are not clean terminal-value sensitivities. Property tax should be given its own independent valuation-yield input before relying on this row.
A39: F. OPERATING BREAK-EVEN — DSCR PASSES AT BASE; EQUITY IRR IS THE TIGHT ONE
A40: Tenor | B40: Amort (yrs) | C40: Min DSCR | D40: Avg DSCR
A41: 7 yr (base) | B41: 4 | C41: 1.417 | D41: 2.54
A42: 10 yr | B42: 7 | C42: 1.997 | D42: 4.181
A43: 12 yr | B43: 9 | C43: 2.24 | D43: 5.792
A44: 15 yr | B44: 12 | C44: 2.473 | D44: 9.488
A45: 18 yr | B45: 15 | C45: 2.608 | D45: 10.029
A46: RECOMPUTED. The 25%/75% debt/equity funding split gives min DSCR 1.42x at the shortest realistic 7-yr tenor, clear of the 1.30x covenant. A longer tenor adds further headroom (10-yr: 2.00x). DSCR is a pre-dividend cash metric and is unaffected by the tax corrections; equity IRR is.
A48: THREE ANSWERS (recomputed): on COST the asset breaks even with a deep cushion (0.087x occupancy/rent, 31.1% exit cap, sale price irrelevant). On DEBT SERVICE the 25%/75% structure clears the 1.30x covenant (min DSCR 1.42x) but this is the TIGHTEST test - it fails first under cost overrun (>~7%), occupancy below 0.85x, or a debt rate above 25.3%. On the PROJECT IRR hurdle (20%) it clears comfortably (28.3%). On the EQUITY IRR hurdle (24%) it now clears, but by only 0.19 percentage points (24.19%) - too thin to treat as a margin of safety.
A50: AUDIT NOTE: this sheet has been fully RECOMPUTED against the corrected live model using a validated replica (base-case agreement 1.6e-14). Break-evens solved by bisection. Values are COMPUTED CONSTANTS, not live formulas - re-run after any Assumptions change. The 24% equity hurdle now has a source cell at Assumptions!B98 (EQ_HURDLE); confirm it.

Sheet Sensitivity
A1: Sensitivity & Scenarios
A2: A. CONSTRUCTION DELAY - isolated (same scope/cost, later completion only)
A3: Delay | B3: Months | C3: Grace (yrs) | D3: IDC | E3: Capex | F3: Project IRR | G3: Min DSCR
A4: Base | B4: 36 | C4: 3 | D4: =IDC_TOTAL -> 3.6053747e+08 | E4: =CAPEX -> 6.8537994e+09 | F4: =Returns!$B$12 -> 0.28306433 | G4: =Returns!$B$19 -> 1.4172968
A5: +6mo | B5: 42 | C5: 3 | D5: 425072863 | E5: 6918334840 | F5: 0.2507 | G5: 1.403
A6: +12mo | B6: 48 | C6: 3 | D6: 490598326 | E6: 6983860303 | F6: 0.257 | G6: 1.39
A7: +24mo | B7: 60 | C7: 3 | D7: 624687228 | E7: 7117949205 | F7: 0.2354 | G7: 1.363
A8: Grace fixed at 3 yrs regardless of delay. RECOMPUTED against the corrected model. NOTE: +6mo and +12mo both push commissioning into the SAME annual period (this is an annual model; construction years = ceil(months/12), so 42m and 48m both = 4 construction years). +6mo therefore shows a LOWER IRR than +12mo only because it front-loads the S-curve spend into fewer years, not because a shorter delay is worse. The original workbook showed the same reversal. A sub-annual delay cannot be modelled faithfully at annual granularity.
A10: B. CONSTRUCTION COST OVERRUN (generic, on top of the VE package)
A11: Overrun | B11: Capex | C11: Project IRR | D11: Equity IRR | E11: Margin | F11: Min DSCR
A12: 0 | B12: =CAPEX -> 6.8537994e+09 | C12: =Returns!$B$12 -> 0.28306433 | D12: =Returns!$B$14 -> 0.2419003 | E12: =Returns!$B$27 -> 9.1502766e+09 | F12: =Returns!$B$19 -> 1.4172968
A13: 0.05 | B13: 7104609357 | C13: 0.2757 | D13: 0.2347 | E13: 8899466733 | F13: 1.365
A14: 0.1 | B14: 7355419269 | C14: 0.2688 | D14: 0.228 | E14: 8648656820 | F14: 1.317
A15: 0.15 | B15: 7606229182 | C15: 0.2623 | D15: 0.2217 | E15: 8397846908 | F15: 1.273
A16: 0.2 | B16: 7857039094 | C16: 0.2562 | D16: 0.2157 | E16: 8147036996 | F16: 1.232
A17: RECOMPUTED. A 20% overrun still clears the 20% project hurdle (25.6%) but pushes min DSCR to 1.23x -- a COVENANT BREACH (1.30x). The covenant, not the IRR hurdle, is the binding constraint on cost overrun: the breach begins between +5% and +10%.
A19: C. FX - 35% of capex USD-linked (CLIENT-AGREED ESTIMATE, not sourced)
A20: Add'l depreciation | B20: Capex | C20: Project IRR | D20: Equity IRR | E20: Margin
A21: 0 | B21: =CAPEX -> 6.8537994e+09 | C21: =Returns!$B$12 -> 0.28306433 | D21: =Returns!$B$14 -> 0.2419003 | E21: =Returns!$B$27 -> 9.1502766e+09
A22: 0.1 | B22: 7029366383 | C22: 0.2779 | D22: 0.2368 | E22: 8974709707
A23: 0.2 | B23: 7204933322 | C23: 0.2729 | D23: 0.232 | E23: 8799142768
A24: 0.3 | B24: 7380500260 | C24: 0.2682 | D24: 0.2274 | E24: 8623575829
A25: RECOMPUTED. Modelled as a cost uplift of 0.35 x devaluation on construction works (35% USD-linked share, CLIENT-AGREED ESTIMATE, not sourced). Replace the 35% share with a real BOQ import breakdown before reliance.
A27: D1. STABILISED OCCUPANCY LEVEL
A28: Occ. multiplier | B28: Project IRR | C28: Equity IRR | D28: Margin | E28: Min DSCR
A29: 0.8 | B29: 0.2621 | C29: 0.2208 | D29: 7146805338 | E29: 1.264
A30: 0.9 | B30: 0.2729 | C30: 0.2316 | D30: 8148540992 | E30: 1.341
A31: 1.00x (base) | B31: =Returns!$B$12 -> 0.28306433 | C31: =Returns!$B$14 -> 0.2419003 | D31: =Returns!$B$27 -> 9.1502766e+09 | E31: =Returns!$B$19 -> 1.4172968
A32: 1.05 | B32: 0.288 | C32: 0.2468 | D32: 9651144472 | E32: 1.456
A34: D2. HOTEL TURNOVER-RENT RATE (IFRS 16 variable lease payment)
A35: Rate | B35: Project IRR | C35: Margin
A36: 0.15 | B36: 0.2816 | C36: 8930964014
A37: 0.2 | B37: 0.2823 | C37: 9040620330
A38: 25% (base) | B38: =Returns!$B$12 -> 0.28306433 | C38: =Returns!$B$27 -> 9.1502766e+09
A39: 0.3 | B39: 0.2838 | C39: 9259932961
A40: 0.35 | B40: 0.2845 | C40: 9369589276
A42: D3. BASEMENT WAREHOUSE RENT (NO SOURCED COMPARABLE)
A43: ETB/m2/mo | B43: Project IRR | C43: Margin
A44: 1500 | B44: 0.2668 | C44: 7575488828
A45: 2500 | B45: 0.2751 | C45: 8362882737
A46: 3,500 (base) | B46: =Returns!$B$12 -> 0.28306433 | C46: =Returns!$B$27 -> 9.1502766e+09
A47: 4500 | B47: 0.2907 | C47: 9937670554
A48: 5500 | B48: 0.298 | C48: 10725064462
A49: RECOMPUTED. Still the most valuable next input to source. At 1,500 min DSCR falls to 1.30x -- exactly at the covenant, so the warehouse rent assumption is load-bearing for the covenant, not just for returns.
A51: D4. RENT ESCALATION p.a. (opex tracks inflation at 5% regardless)
A52: Rent esc. | B52: Project IRR | C52: Margin
A53: 0.15 | B53: 0.225 | C53: 5765176013
A54: 0.2 | B54: 0.2536 | C54: 7384697246
A55: 25% (base) | B55: =Returns!$B$12 -> 0.28306433 | C55: =Returns!$B$27 -> 9.1502766e+09
A56: 0.3 | B56: 0.3132 | C56: 11067999967
A57: 0.35 | B57: 0.3439 | C57: 13143952969
A58: RECOMPUTED. Still the largest single lever in the tornado. 25% p.a. is an unusually high assumption -- the single biggest driver of how strong these numbers look. At 15% escalation project IRR falls to 22.5%, still above the 20% hurdle but with far less cushion.
A60: E1. INTEREST RATE
A61: Rate | B61: Project IRR | C61: Equity IRR | D61: Min DSCR
A62: 0.14 | B62: 0.2856 | C62: 0.2474 | D62: 1.578
A63: 0.18 | B63: 0.2839 | C63: 0.2437 | D63: 1.467
A64: 20% (base) | B64: =Returns!$B$12 -> 0.28306433 | C64: =Returns!$B$14 -> 0.2419003 | D64: =Returns!$B$19 -> 1.4172968
A65: 0.24 | B65: 0.2814 | C65: 0.2382 | D65: 1.326
A66: RECOMPUTED. Project IRR barely moves (unlevered); equity IRR and DSCR are the sensitive ones. DSCR clears 1.30x even at 24%. Equity IRR clears its 24% hurdle at base (24.19%) but the margin is thin -- it falls below at rates above roughly 21%.
A68: E2. EXIT CAP RATE
A69: Exit cap | B69: Project IRR | C69: GDV | D69: Margin
A70: 0.08 | B70: 0.2837 | C70: 19860624543 | D70: 13006825099
A71: 0.095 | B71: 0.2833 | C71: 17336004672 | D71: 10482205227
A72: 10.5% (base) | B72: =Returns!$B$12 -> 0.28306433 | C72: =Returns!$B$25 -> 1.6004076e+10 | D72: =Returns!$B$27 -> 9.1502766e+09
A73: 0.12 | B73: 0.2827 | C73: 14379026665 | D73: 7525227221
A74: RECOMPUTED. WARNING: EXIT_CAP does DOUBLE DUTY in this model -- it is both the terminal cap rate (Returns!B9) AND the capitalisation rate in the property-tax market-value proxy (Opex!row12 divides by EXIT_CAP). A lower cap rate therefore raises terminal value but also inflates property tax, and the two effects partly cancel. That is why project IRR barely moves across this table. This is a MODEL DESIGN issue, not a result: property tax should use its own independent valuation-yield input.
A75: F. MASTER TORNADO - ranked by |delta| on project IRR (hurdle 20%)
A76: Driver | B76: IRR | C76: Delta (pts) | D76: Margin | E76: Min DSCR
A77: Rent escalation 35% | B77: 0.3439 | C77: 6.08 | D77: 13143952969 | E77: 1.524
A78: Rent escalation 15% | B78: 0.225 | C78: -5.81 | D78: 5765176013 | E78: 1.311
A79: Delay +24mo | B79: 0.2354 | C79: -4.76 | D79: 8886126884 | E79: 1.363
A80: Delay +6mo | B80: 0.2507 | C80: -3.24 | D80: 9085741249 | E80: 1.403
A81: Cost overrun +20% | B81: 0.2562 | C81: -2.69 | D81: 8147036996 | E81: 1.232
A82: Delay +12mo | B82: 0.257 | C82: -2.61 | D82: 9020215786 | E82: 1.39
A83: Occupancy -20% | B83: 0.2621 | C83: -2.09 | D83: 7146805338 | E83: 1.264
A84: Warehouse rent 1,500 | B84: 0.2668 | C84: -1.63 | D84: 7575488828 | E84: 1.297
A85: Warehouse rent 5,500 | B85: 0.298 | C85: 1.5 | D85: 10725064462 | E85: 1.538
A86: FX shock +30% (35% share) | B86: 0.2682 | C86: -1.49 | D86: 8623575829 | E86: 1.312
A87: Cost overrun +10% | B87: 0.2688 | C87: -1.42 | D87: 8648656820 | E87: 1.317
A88: Occupancy -10% | B88: 0.2729 | C88: -1.02 | D88: 8148540992 | E88: 1.341
... A95: Exit cap 12% | B95: 0.2827 | C95: -0.04 | D95: 7525227221 | E95: 1.433
A96: BASE | B96: =Returns!$B$12 -> 0.28306433 | C96: 0 | D96: =Returns!$B$27 -> 9.1502766e+09 | E96: =Returns!$B$19 -> 1.4172968
A97: RECOMPUTED. Delta column in PERCENTAGE POINTS. Project IRR clears its 20% hurdle in every single-driver downside tested. Equity IRR clears 24% at base (24.19%) but only just. The binding risk is the DSCR covenant: cost overrun +20% (1.23x), occupancy -20% (1.26x) and warehouse rent 1,500 (1.30x) all reach or breach the 1.30x covenant while project IRR still looks healthy. Read the DSCR column, not the IRR column, for covenant risk.
A99: G. SCENARIOS - base / upside / downside (stacked, correlated stresses)
A100: Scenario | B100: Capex | C100: Project IRR | D100: Equity IRR | E100: Margin | F100: Min DSCR
A101: BASE | B101: =CAPEX -> 6.8537994e+09 | C101: =Returns!$B$12 -> 0.28306433 | D101: =Returns!$B$14 -> 0.2419003 | E101: =Returns!$B$27 -> 9.1502766e+09 | F101: =Returns!$B$19 -> 1.4172968
A102: UPSIDE (occ +5%, hotel 30%, debt 16%) | B102: 6779237907 | C102: 0.2904 | D102: 0.2512 | E102: 9835362325 | F102: 1.574
A103: DOWNSIDE (1yr delay+10% overrun+occ -10%+debt 24%) | B103: 7613901952 | C103: 0.2335 | D103: 0.1965 | E103: 7388438484 | F103: 1.144
A104: SEVERE DOWNSIDE (2yr delay+15% overrun+FX20%+occ -15%) | B104: 8334793367 | C104: 0.1992 | D104: 0.1681 | E104: 6166679242 | F104: 1.085
A105: RECOMPUTED. SEVERE DOWNSIDE lands almost exactly ON the 20% project hurdle (19.9%) and breaches the DSCR covenant badly (1.09x). DOWNSIDE also breaches the covenant (1.14x) while still clearing the project IRR hurdle (23.4%). Equity IRR clears 24% only at BASE and UPSIDE. In both downside cases the DSCR covenant fails BEFORE the IRR hurdle does -- the covenant is the real constraint.
A108: Hurdles: project IRR 20% | equity IRR 24% | DSCR covenant 1.30x. RECOMPUTED against the corrected model (fixed FF&E depreciation life, VAT refund in IRR cash flows). At base: project IRR 28.3% (clears), equity IRR 24.19% (clears, but by only 0.19pts), min DSCR 1.42x (clears).
A110: AUDIT NOTE: every figure in this sheet has now been RECOMPUTED against the corrected live model by re-running each scenario through a validated replica of the workbook (agreement with the workbook at base case: 1.6e-14 relative). Values remain COMPUTED CONSTANTS, not live formulas -- only the 'Base' rows are live links. Re-run this sheet after any Assumptions change.

Sheet Dashboard
A1: Dashboard — key outputs
A2: All values are live links. Nothing here is typed.
A3: Liiban Smart Mall · TDOMA S.C. · ETB · v2.0 · 20 July 2026
A5: CAPEX & FUNDING
A6: Total capex (incl. land in-kind) | B6: =CAPEX -> 6.8537994e+09
A7: of which land (non-cash) | B7: =LAND_V -> 1650000000
A8: Cash requirement | B8: =CASH_REQ -> 5.3237994e+09
A9: TDOMA equity | B9: =EQ_TDOMA -> 3.9928496e+09
A10: Debt | B10: =DEBT_V -> 1.3309499e+09
A11: Sources − Uses | B11: =Capex!$B$29 -> 0 | C11: Must be zero
A12: Capex USD @160 | B12: =CAPEX/FX -> 42836247
A14: RETURNS
A15: Project NPV @20% | B15: =Returns!$B$11 -> 2.8607793e+09 | C15: Negative = does not clear the hurdle
A16: Project IRR | B16: =Returns!$B$12 -> 0.28306433
A17: Equity NPV @20% | B17: =Returns!$B$13 -> 1.1195424e+09
A18: Equity IRR | B18: =Returns!$B$14 -> 0.2419003
A19: Yield on cost | B19: =Returns!$B$16 -> 0.1754967 | C19: Compare to the loan interest rate
A20: Minimum DSCR | B20: =Returns!$B$19 -> 1.4172968 | C20: Covenant 1.30x
A22: VIABILITY — GDV vs COST
A23: Total GDV | B23: =Returns!$B$25 -> 1.6004076e+10
A24: Total capex | B24: =Returns!$B$26 -> 6.8537994e+09
A25: Development margin | B25: =Returns!$B$27 -> 9.1502766e+09
A26: Profit on cost | B26: =Returns!$B$28 -> 1.3350663
A28: CHECKS
A29: Integrity checks passing | B29: =Checks!$B$17 -> 13 / 13
A31: READ THIS
A32: Value-engineered: curtain walling (was kinetic facade), cloud infrastructure (was on-site data
A33: centre), ASRS dropped with B2+B3 let as warehouse instead, office consolidated to 5,264 m2, key
A34: money removed (TDOMA cannot charge it — see Assumptions).
A35: ="Project IRR "&TEXT(Returns!$B$12,"0.0%")&", equity IRR "&TEXT(Returns!$B$14,"0.0%")&" — "&IF(Returns!$B$12>=DISC,"clears","MISSES")&" the "&TEXT(DISC,"0%")&" project hurdle; "&IF(Returns!$B$14>=EQ_HURDLE,"clears","MISSES")&" the "&TEXT(EQ_HURDLE,"0%")&" equity hurdle." -> Project IRR 28.3%, equity IRR 24.2% — clears the 20% project hurdle; clears the 24% equity hurdle.
A36: ="Minimum DSCR is "&TEXT(Returns!$B$19,"0.00")&"x — "&IF(Returns!$B$19>=DSCR_COV,"clears","BREACHES")&" the "&TEXT(DSCR_COV,"0.00")&"x covenant." -> Minimum DSCR is 1.42x — clears the 1.30x covenant.
A37: Warehouse rent is an ESTIMATE with no sourced comparable — the single most valuable next input to obtain.
