Workbook

Sheet Summary
A1: BOQ Summary & Capital Structure (ETB)
A2: Elemental construction summary, then the full capex and funding structure. Ties exactly to the financial model.
A3: Element | B3: Amount ETB | C3: % of capex | D3: Note
A4: A Preliminaries & General | B4: ='Detailed BOQ'!F12 -> 377096310 | C4: =B4/$B$25 -> 0.072465573 | D4: 7 items
A5: B Substructure | B5: ='Detailed BOQ'!F25 -> 616199550 | C5: =B5/$B$25 -> 0.11841339 | D5: 11 items
A6: C Superstructure - Frame, Floors & Roof | B6: ='Detailed BOQ'!F34 -> 637545000 | C6: =B6/$B$25 -> 0.12251529 | D6: 7 items
A7: D External Envelope | B7: ='Detailed BOQ'!F40 -> 421106280 | C7: =B7/$B$25 -> 0.08092285 | D7: 4 items
A8: E Internal Divisions | B8: ='Detailed BOQ'!F46 -> 146718000 | C8: =B8/$B$25 -> 0.028194399 | D8: 4 items
A9: F Finishes | B9: ='Detailed BOQ'!F54 -> 339989680 | C9: =B9/$B$25 -> 0.065334893 | D9: 6 items
A10: G Fittings & Sanitary | B10: ='Detailed BOQ'!F58 -> 99915770 | C10: =B10/$B$25 -> 0.019200542 | D10: 2 items
A11: H Services / Mep | B11: ='Detailed BOQ'!F70 -> 799684370 | C11: =B11/$B$25 -> 0.15367317 | D11: 10 items
A12: I Specialist Systems | B12: ='Detailed BOQ'!F77 -> 543934690 | C12: =B12/$B$25 -> 0.10452645 | D12: 5 items
A13: J External Works (2,000 M2 Surface) | B13: ='Detailed BOQ'!F86 -> 81910350 | C13: =B13/$B$25 -> 0.015740489 | D13: 7 items
A14: TOTAL CONSTRUCTION WORKS (BOQ A-J) | B14: ='Detailed BOQ'!F87 -> 4064100000 | C14: =B14/$B$25 -> 0.78098705 | D14: Sum of the 10 BOQ elements
A16: DEVELOPMENT COST / CAPEX
A17: Construction works (BOQ A-J) | B17: =B14 -> 4064100000 | C17: =B17/$B$25 -> 0.78098705 | D17: Sum of the 10 BOQ elements
A18: In-house design @2% | B18: =0.02*B17 -> 81282000 | C18: =B18/$B$25 -> 0.015619741 | D18: TDOMA staff cost, capitalised per IAS 16.17(a); general overhead excluded per IAS 16.19(d)
A19: Specialist consultancy | B19: 16849500 | C19: =B19/$B$25 -> 0.0032379226 | D19: Industry norm, not a vendor quotation - specialist systems need external design
A20: Contingency @12% | B20: =0.12*(B17+B18+B19) -> 499467780 | C20: =B20/$B$25 -> 0.095981366 | D20: On construction + design + specialist
A21: Capital works | B21: =B17+B18+B19+B20 -> 4661699280 | C21: =B21/$B$25 -> 0.89582608
A22: FF&E - TDOMA scope | B22: 163020000 | C22: =B22/$B$25 -> 0.03132711 | D22: Common areas + HQ + hire-out venues. Operator fits out hotel; tenants fit out demises.
A23: IDC (IAS 23, capitalised) | B23: 360537467 | C23: =B23/$B$25 -> 0.069283505 | D23: Solved monthly on the IDC sheet - model is fully acyclic, no iteration needed
A24: Arrangement fee @1.5% | B24: 18542697 | C24: =B24/$B$25 -> 0.0035632997 | D24: Borrowing cost - IAS 23
A25: Building sub-total (CASH) | B25: =B21+B22+B23+B24 -> 5203799444 | C25: =B25/$B$25 -> 1
A26: Land (in-kind, NON-CASH) | B26: 1650000000 | C26: =B26/$B$25 -> 0.31707602 | D26: City's PPP contribution
A27: TOTAL CAPEX / DEVELOPMENT COST | B27: =B25+B26 -> 6853799444 | C27: =100% -> 1
A28: Pre-opening & marketing | B28: 120000000
A29: TOTAL USES | B29: =B27+B28 -> 6973799444
A31: FUNDING
A32: Cash requirement (ex-land) | B32: =B29-B26 -> 5323799444
A33: TDOMA equity (75% of cash) | B33: =0.75*B32 -> 3992849583
A34: City land (in-kind, non-cash) | B34: =B26 -> 1650000000
A35: Debt (25% of cash) | B35: =0.25*B32 -> 1330949861
A36: TOTAL SOURCES | B36: =B33+B26+B35 -> 6973799444
A37: CHECK: Sources - Uses | B37: =B36-B29 -> 0 | D37: Must be zero
A39: Input VAT recoverable on capex (refunded in year 1) | B39: 629311210
A40: Memo - USD @160 | B40: =B27/160 -> 42836247 | D40: Reference
A41: Capex per gross m2 | B41: 181317 | D41: Total capex / gross building area
A42: EFFECTIVE capex per TDOMA gross m2 (70%) | B42: 259025 | D42: TDOMA's 70% economic share of the building
A44: Note: elemental estimate at concept stage; re-measure from detailed drawings before tender. Rates in ETB, current mid-2026; verify with a quantity surveyor and current supplier quotations. Land is the City's non-cash PPP contribution; capitalised costs follow IAS 16/IAS 23 as noted.

Sheet Detailed BOQ
A1: Detailed Bill of Quantities (elemental / preliminary) - ETB
A2: Concept-stage elemental BOQ. Blue = input (Qty, Rate). Amount = Qty x Rate. Re-measure from detailed drawings before tender.
A3: Item | B3: Description | C3: Unit | D3: Qty | E3: Rate ETB | F3: Amount ETB
A4: A | B4: PRELIMINARIES & GENERAL
A5: A.1 | B5: Site establishment, hoarding, offices & welfare | C5: sum | D5: 1 | E5: 40021990 | F5: =D5*E5 -> 40021990
A6: A.2 | B6: Site management, supervision & staff | C6: month | D6: 36 | E6: 4002200 | F6: =D6*E6 -> 144079200
A7: A.3 | B7: Insurances, performance bond & permits | C7: sum | D7: 1 | E7: 48915770 | F7: =D7*E7 -> 48915770
A8: A.4 | B8: Temporary services (power, water, telecoms) | C8: sum | D8: 1 | E8: 26681330 | F8: =D8*E8 -> 26681330
A9: A.5 | B9: Health, safety & environmental management | C9: sum | D9: 1 | E9: 31128220 | F9: =D9*E9 -> 31128220
A10: A.6 | B10: Tower crane, hoists & major plant | C10: month | D10: 36 | E10: 1778760 | F10: =D10*E10 -> 64035360
A11: A.7 | B11: Testing, commissioning & handover | C11: sum | D11: 1 | E11: 22234440 | F11: =D11*E11 -> 22234440
B12: Subtotal A | F12: =SUM(F5:F11) -> 377096310
A13: B | B13: SUBSTRUCTURE
A14: B.1 | B14: Site clearance & strip | C14: m2 | D14: 5000 | E14: 360 | F14: =D14*E14 -> 1800000
A15: B.2 | B15: Bulk excavation for 3 basement levels | C15: m3 | D15: 42000 | E15: 1070 | F15: =D15*E15 -> 44940000
A16: B.3 | B16: Secant/contiguous pile retaining wall | C16: m2 | D16: 3600 | E16: 24900 | F16: =D16*E16 -> 89640000
A17: B.4 | B17: Dewatering during construction | C17: sum | D17: 1 | E17: 35575110 | F17: =D17*E17 -> 35575110
A18: B.5 | B18: Cart away & disposal of surplus | C18: m3 | D18: 42000 | E18: 620 | F18: =D18*E18 -> 26040000
A19: B.6 | B19: Blinding / lean concrete | C19: m2 | D19: 3000 | E19: 2220 | F19: =D19*E19 -> 6660000
A20: B.7 | B20: RC raft foundation | C20: m3 | D20: 3600 | E20: 28460 | F20: =D20*E20 -> 102456000
A21: B.8 | B21: RC basement retaining walls | C21: m3 | D21: 2400 | E21: 30240 | F21: =D21*E21 -> 72576000
A22: B.9 | B22: RC basement columns, beams & slabs (3 levels) | C22: m2 | D22: 9000 | E22: 19570 | F22: =D22*E22 -> 176130000
A23: B.10 | B23: Tanking / waterproofing to basement | C23: m2 | D23: 6600 | E23: 5780 | F23: =D23*E23 -> 38148000
A24: B.11 | B24: Basement drainage, sumps & pumps | C24: sum | D24: 1 | E24: 22234440 | F24: =D24*E24 -> 22234440
B25: Subtotal B | F25: =SUM(F14:F24) -> 616199550
A26: C | B26: SUPERSTRUCTURE - FRAME, FLOORS & ROOF
A27: C.1 | B27: RC columns (above grade) | C27: m3 | D27: 3200 | E27: 26680 | F27: =D27*E27 -> 85376000
A28: C.2 | B28: RC beams | C28: m3 | D28: 4000 | E28: 25790 | F28: =D28*E28 -> 103160000
A29: C.3 | B29: Transfer structure at podium/tower interface | C29: m3 | D29: 900 | E29: 40020 | F29: =D29*E29 -> 36018000
A30: C.4 | B30: Suspended RC floor slabs (above grade) | C30: m2 | D30: 28800 | E30: 12450 | F30: =D30*E30 -> 358560000
A31: C.5 | B31: RC roof slab & parapets | C31: m2 | D31: 1200 | E31: 13340 | F31: =D31*E31 -> 16008000
A32: C.6 | B32: RC staircases (all cores) | C32: m2 | D32: 1600 | E32: 16010 | F32: =D32*E32 -> 25616000
A33: C.7 | B33: Vehicle ramps | C33: m2 | D33: 900 | E33: 14230 | F33: =D33*E33 -> 12807000
B34: Subtotal C | F34: =SUM(F27:F33) -> 637545000
A35: D | B35: EXTERNAL ENVELOPE
A36: D.1 | B36: Unitised curtain walling / structural glazing | C36: m2 | D36: 8500 | E36: 28460 | F36: =D36*E36 -> 241910000
A37: D.2 | B37: Kinetic bronze facade shading system | C37: m2 | D37: 3500 | E37: 40020 | F37: =D37*E37 -> 140070000
A38: D.3 | B38: Solid cladding / rendered external walls | C38: m2 | D38: 2500 | E38: 10670 | F38: =D38*E38 -> 26675000
A39: D.4 | B39: Main entrance portals & revolving doors | C39: no | D39: 4 | E39: 3112820 | F39: =D39*E39 -> 12451280
B40: Subtotal D | F40: =SUM(F36:F39) -> 421106280
A41: E | B41: INTERNAL DIVISIONS
A42: E.1 | B42: Blockwork / partition walls | C42: m2 | D42: 22000 | E42: 2850 | F42: =D42*E42 -> 62700000
A43: E.2 | B43: Fire-rated & acoustic partitions | C43: m2 | D43: 6000 | E43: 4000 | F43: =D43*E43 -> 24000000
A44: E.3 | B44: Glazed internal partitions | C44: m2 | D44: 3000 | E44: 8000 | F44: =D44*E44 -> 24000000
A45: E.4 | B45: Internal doors (all types) | C45: no | D45: 900 | E45: 40020 | F45: =D45*E45 -> 36018000
B46: Subtotal E | F46: =SUM(F42:F45) -> 146718000
A47: F | B47: FINISHES
A48: F.1 | B48: Floor finishes - retail & public (tile/stone) | C48: m2 | D48: 12000 | E48: 5780 | F48: =D48*E48 -> 69360000
A49: F.2 | B49: Floor finishes - offices & back of house | C49: m2 | D49: 8000 | E49: 3110 | F49: =D49*E49 -> 24880000
A50: F.3 | B50: Floor finishes - hotel & serviced apts (premium) | C50: m2 | D50: 3500 | E50: 7560 | F50: =D50*E50 -> 26460000
A51: F.4 | B51: Wall finishes, plaster & paint | C51: m2 | D51: 60000 | E51: 1250 | F51: =D51*E51 -> 75000000
A52: F.5 | B52: Suspended ceilings | C52: m2 | D52: 26000 | E52: 2850 | F52: =D52*E52 -> 74100000
A53: F.6 | B53: Feature finishes (lobbies, atrium, rooftop) | C53: sum | D53: 1 | E53: 70189680 | F53: =D53*E53 -> 70189680
B54: Subtotal F | F54: =SUM(F48:F53) -> 339989680
A55: G | B55: FITTINGS & SANITARY
A56: G.1 | B56: Sanitary fittings & toilet fit-out | C56: WC grp | D56: 60 | E56: 850000 | F56: =D56*E56 -> 51000000
A57: G.2 | B57: Built-in joinery, reception counters & signage | C57: sum | D57: 1 | E57: 48915770 | F57: =D57*E57 -> 48915770
B58: Subtotal G | F58: =SUM(F56:F57) -> 99915770
A59: H | B59: SERVICES / MEP
A60: H.1 | B60: Cold & hot water supply, tanks & pumps | C60: m2 | D60: 37800 | E60: 1600 | F60: =D60*E60 -> 60480000
A61: H.2 | B61: Soil, waste & rainwater drainage | C61: m2 | D61: 37800 | E61: 1070 | F61: =D61*E61 -> 40446000
A62: H.3 | B62: HVAC - ventilation & cooling | C62: m2 | D62: 37800 | E62: 4890 | F62: =D62*E62 -> 184842000
A63: H.4 | B63: Electrical LV distribution & small power | C63: m2 | D63: 37800 | E63: 3380 | F63: =D63*E63 -> 127764000
A64: H.5 | B64: Standby generators & transformers | C64: no | D64: 3 | E64: 19566310 | F64: =D64*E64 -> 58698930
A65: H.6 | B65: Lighting (internal & feature) | C65: m2 | D65: 37800 | E65: 1420 | F65: =D65*E65 -> 53676000
A66: H.7 | B66: Fire detection, sprinklers & hydrants | C66: m2 | D66: 37800 | E66: 1960 | F66: =D66*E66 -> 74088000
A67: H.8 | B67: Passenger & goods lifts | C67: no | D67: 8 | E67: 10672530 | F67: =D67*E67 -> 85380240
A68: H.9 | B68: Escalators (podium) | C68: no | D68: 8 | E68: 8004400 | F68: =D68*E68 -> 64035200
A69: H.10 | B69: BMS, ELV, data & IoT cabling | C69: m2 | D69: 37800 | E69: 1330 | F69: =D69*E69 -> 50274000
B70: Subtotal H | F70: =SUM(F60:F69) -> 799684370
A71: I | B71: SPECIALIST SYSTEMS
A72: I.1 | B72: Automated logistics (ASRS / AGV / cross-dock) | C72: sum | D72: 1 | E72: 292513600 | F72: =D72*E72 -> 292513600
A73: I.2 | B73: Data centre / cloud node fit-out | C73: sum | D73: 1 | E73: 106725320 | F73: =D73*E73 -> 106725320
A74: I.3 | B74: Hydraulic 2-car stacking parking system | C74: platform | D74: 65 | E74: 550000 | F74: =D74*E74 -> 35750000
A75: I.4 | B75: Bonded & cold storage fit-out | C75: m2 | D75: 1500 | E75: 40020 | F75: =D75*E75 -> 60030000
A76: I.5 | B76: Cashless, access-control & security systems | C76: sum | D76: 1 | E76: 48915770 | F76: =D76*E76 -> 48915770
B77: Subtotal I | F77: =SUM(F72:F76) -> 543934690
A78: J | B78: EXTERNAL WORKS (2,000 m2 surface)
A79: J.1 | B79: Site paving & hardstanding | C79: m2 | D79: 1400 | E79: 5780 | F79: =D79*E79 -> 8092000
A80: J.2 | B80: Surface parking equipment & markings | C80: sum | D80: 1 | E80: 5336270 | F80: =D80*E80 -> 5336270
A81: J.3 | B81: Loading dock apron, levellers & equipment | C81: no | D81: 4 | E81: 4002200 | F81: =D81*E81 -> 16008800
A82: J.4 | B82: Soft landscaping, seating & water feature | C82: sum | D82: 1 | E82: 17787550 | F82: =D82*E82 -> 17787550
A83: J.5 | B83: Boundary wall, gates & gatehouse | C83: sum | D83: 1 | E83: 10672530 | F83: =D83*E83 -> 10672530
A84: J.6 | B84: External drainage & utility connections | C84: sum | D84: 1 | E84: 16008800 | F84: =D84*E84 -> 16008800
A85: J.7 | B85: Site lighting & external power | C85: sum | D85: 1 | E85: 8004400 | F85: =D85*E85 -> 8004400
B86: Subtotal J | F86: =SUM(F79:F85) -> 81910350
B87: TOTAL CONSTRUCTION WORKS (A-J) | F87: =F12+F25+F34+F40+F46+F54+F58+F70+F77+F86 -> 4064100000
